package com.g.a;

class t
  extends Thread
{
  t(s params) {}
  
  /* Error */
  public void run()
  {
    // Byte code:
    //   0: aload_0
    //   1: getfield 10	com/g/a/t:a	Lcom/g/a/s;
    //   4: getfield 23	com/g/a/s:b	Ljava/lang/Object;
    //   7: astore_1
    //   8: aload_1
    //   9: monitorenter
    //   10: aload_0
    //   11: getfield 10	com/g/a/t:a	Lcom/g/a/s;
    //   14: getfield 23	com/g/a/s:b	Ljava/lang/Object;
    //   17: invokevirtual 28	java/lang/Object:notifyAll	()V
    //   20: aload_0
    //   21: getfield 10	com/g/a/t:a	Lcom/g/a/s;
    //   24: getfield 32	com/g/a/s:c	Landroid/content/Context;
    //   27: aload_0
    //   28: getfield 10	com/g/a/t:a	Lcom/g/a/s;
    //   31: getfield 35	com/g/a/s:a	Landroid/content/BroadcastReceiver;
    //   34: invokevirtual 41	android/content/Context:unregisterReceiver	(Landroid/content/BroadcastReceiver;)V
    //   37: aload_1
    //   38: monitorexit
    //   39: return
    //   40: astore_2
    //   41: aload_0
    //   42: getfield 10	com/g/a/t:a	Lcom/g/a/s;
    //   45: getfield 32	com/g/a/s:c	Landroid/content/Context;
    //   48: aload_0
    //   49: getfield 10	com/g/a/t:a	Lcom/g/a/s;
    //   52: getfield 35	com/g/a/s:a	Landroid/content/BroadcastReceiver;
    //   55: invokevirtual 41	android/content/Context:unregisterReceiver	(Landroid/content/BroadcastReceiver;)V
    //   58: goto -21 -> 37
    //   61: astore_2
    //   62: aload_1
    //   63: monitorexit
    //   64: aload_2
    //   65: athrow
    //   66: astore_1
    //   67: return
    //   68: astore_2
    //   69: aload_0
    //   70: getfield 10	com/g/a/t:a	Lcom/g/a/s;
    //   73: getfield 32	com/g/a/s:c	Landroid/content/Context;
    //   76: aload_0
    //   77: getfield 10	com/g/a/t:a	Lcom/g/a/s;
    //   80: getfield 35	com/g/a/s:a	Landroid/content/BroadcastReceiver;
    //   83: invokevirtual 41	android/content/Context:unregisterReceiver	(Landroid/content/BroadcastReceiver;)V
    //   86: aload_2
    //   87: athrow
    // Local variable table:
    //   start	length	slot	name	signature
    //   0	88	0	this	t
    //   7	56	1	localObject1	Object
    //   66	1	1	localThrowable1	Throwable
    //   40	1	2	localThrowable2	Throwable
    //   61	4	2	localObject2	Object
    //   68	19	2	localObject3	Object
    // Exception table:
    //   from	to	target	type
    //   10	20	40	java/lang/Throwable
    //   20	37	61	finally
    //   37	39	61	finally
    //   41	58	61	finally
    //   62	64	61	finally
    //   69	88	61	finally
    //   0	10	66	java/lang/Throwable
    //   64	66	66	java/lang/Throwable
    //   10	20	68	finally
  }
}


/* Location:              /Users/gaoht/Downloads/zirom/classes2-dex2jar.jar!/com/g/a/t.class
 * Java compiler version: 6 (50.0)
 * JD-Core Version:       0.7.1
 */