package com.unionpay.sdk;

import android.content.BroadcastReceiver;
import android.content.Context;

final class ba
  extends BroadcastReceiver
{
  ba(Object paramObject, Context paramContext) {}
  
  /* Error */
  public final void onReceive(Context paramContext, android.content.Intent paramIntent)
  {
    // Byte code:
    //   0: aload_0
    //   1: getfield 12	com/unionpay/sdk/ba:a	Ljava/lang/Object;
    //   4: astore_1
    //   5: aload_1
    //   6: monitorenter
    //   7: aload_0
    //   8: getfield 12	com/unionpay/sdk/ba:a	Ljava/lang/Object;
    //   11: invokevirtual 27	java/lang/Object:notifyAll	()V
    //   14: aload_0
    //   15: getfield 14	com/unionpay/sdk/ba:b	Landroid/content/Context;
    //   18: aload_0
    //   19: invokevirtual 33	android/content/Context:unregisterReceiver	(Landroid/content/BroadcastReceiver;)V
    //   22: aload_1
    //   23: monitorexit
    //   24: return
    //   25: astore_2
    //   26: aload_0
    //   27: getfield 14	com/unionpay/sdk/ba:b	Landroid/content/Context;
    //   30: aload_0
    //   31: invokevirtual 33	android/content/Context:unregisterReceiver	(Landroid/content/BroadcastReceiver;)V
    //   34: goto -12 -> 22
    //   37: astore_2
    //   38: aload_1
    //   39: monitorexit
    //   40: aload_2
    //   41: athrow
    //   42: astore_1
    //   43: return
    //   44: astore_2
    //   45: aload_0
    //   46: getfield 14	com/unionpay/sdk/ba:b	Landroid/content/Context;
    //   49: aload_0
    //   50: invokevirtual 33	android/content/Context:unregisterReceiver	(Landroid/content/BroadcastReceiver;)V
    //   53: aload_2
    //   54: athrow
    // Local variable table:
    //   start	length	slot	name	signature
    //   0	55	0	this	ba
    //   0	55	1	paramContext	Context
    //   0	55	2	paramIntent	android.content.Intent
    // Exception table:
    //   from	to	target	type
    //   7	14	25	java/lang/Throwable
    //   14	22	37	finally
    //   22	24	37	finally
    //   26	34	37	finally
    //   45	55	37	finally
    //   0	7	42	java/lang/Throwable
    //   38	42	42	java/lang/Throwable
    //   7	14	44	finally
  }
}


/* Location:              /Users/gaoht/Downloads/zirom/classes2-dex2jar.jar!/com/unionpay/sdk/ba.class
 * Java compiler version: 6 (50.0)
 * JD-Core Version:       0.7.1
 */