package cn.jiguang.c.f;

import android.content.Context;
import cn.jiguang.c.a.e;
import org.json.JSONException;
import org.json.JSONObject;

public final class c
{
  private static final String[] z;
  
  static
  {
    String[] arrayOfString = new String[29];
    int j = 0;
    Object localObject2 = "AMxS3W";
    int i = -1;
    Object localObject1 = arrayOfString;
    char[] arrayOfChar = ((String)localObject2).toCharArray();
    int k = arrayOfChar.length;
    int i1 = 0;
    int m = 0;
    int i3 = i;
    localObject2 = arrayOfChar;
    int i4 = j;
    Object localObject3 = localObject1;
    int n = k;
    Object localObject4;
    int i2;
    if (k <= 1)
    {
      localObject4 = localObject1;
      localObject1 = arrayOfChar;
      i2 = i;
      label68:
      n = m;
      label71:
      localObject2 = localObject1;
      i1 = localObject2[m];
      switch (n % 5)
      {
      default: 
        i = 80;
      }
    }
    for (;;)
    {
      localObject2[m] = ((char)(i ^ i1));
      n += 1;
      if (k == 0)
      {
        m = k;
        break label71;
      }
      i1 = n;
      n = k;
      localObject3 = localObject4;
      i4 = j;
      localObject2 = localObject1;
      i3 = i2;
      i2 = i3;
      localObject1 = localObject2;
      j = i4;
      localObject4 = localObject3;
      k = n;
      m = i1;
      if (n > i1) {
        break label68;
      }
      localObject1 = new String((char[])localObject2).intern();
      switch (i3)
      {
      default: 
        localObject3[i4] = localObject1;
        j = 1;
        localObject2 = "^Mn@<mFcR";
        i = 0;
        localObject1 = arrayOfString;
        break;
      case 0: 
        localObject3[i4] = localObject1;
        j = 2;
        localObject2 = "FK`D#";
        i = 1;
        localObject1 = arrayOfString;
        break;
      case 1: 
        localObject3[i4] = localObject1;
        j = 3;
        localObject2 = "QMcO\017[R";
        i = 2;
        localObject1 = arrayOfString;
        break;
      case 2: 
        localObject3[i4] = localObject1;
        j = 4;
        localObject2 = "\\Gy";
        i = 3;
        localObject1 = arrayOfString;
        break;
      case 3: 
        localObject3[i4] = localObject1;
        j = 5;
        localObject2 = "VCyD";
        i = 4;
        localObject1 = arrayOfString;
        break;
      case 4: 
        localObject3[i4] = localObject1;
        j = 6;
        localObject2 = "K[tX}o E4";
        i = 5;
        localObject1 = arrayOfString;
        break;
      case 5: 
        localObject3[i4] = localObject1;
        j = 7;
        localObject2 = "AWnB5WFRU?B";
        i = 6;
        localObject1 = arrayOfString;
        break;
      case 6: 
        localObject3[i4] = localObject1;
        j = 8;
        localObject2 = "TCdM5V}yN ";
        i = 7;
        localObject1 = arrayOfString;
        break;
      case 7: 
        localObject3[i4] = localObject1;
        j = 9;
        localObject2 = "AVlU9AVdB#vCy@p[Q-O%^N-";
        i = 8;
        localObject1 = arrayOfString;
        break;
      case 8: 
        localObject3[i4] = localObject1;
        j = 10;
        localObject2 = "AFf~9\\FhY";
        i = 9;
        localObject1 = arrayOfString;
        break;
      case 9: 
        localObject3[i4] = localObject1;
        j = 11;
        localObject2 = "^MjH>mDlH<WF";
        i = 10;
        localObject1 = arrayOfString;
        break;
      case 10: 
        localObject3[i4] = localObject1;
        j = 12;
        localObject2 = "F[}D";
        i = 11;
        localObject1 = arrayOfString;
        break;
      case 11: 
        localObject3[i4] = localObject1;
        j = 13;
        localObject2 = "[VdL5";
        i = 12;
        localObject1 = arrayOfString;
        break;
      case 12: 
        localObject3[i4] = localObject1;
        j = 14;
        localObject2 = "^MlEpEPdU5S@aDpVCy@2SQh\0016[Ca";
        i = 13;
        localObject1 = arrayOfString;
        break;
      case 13: 
        localObject3[i4] = localObject1;
        j = 15;
        localObject2 = "^MjH>mVbU1^";
        i = 14;
        localObject1 = arrayOfString;
        break;
      case 14: 
        localObject3[i4] = localObject1;
        j = 16;
        localObject2 = "{LiD(aVlU#";
        i = 15;
        localObject1 = arrayOfString;
        break;
      case 15: 
        localObject3[i4] = localObject1;
        j = 17;
        localObject2 = "AWnB5AQRE5FCdM#";
        i = 16;
        localObject1 = arrayOfString;
        break;
      case 16: 
        localObject3[i4] = localObject1;
        j = 18;
        localObject2 = "QMxO$m\021R";
        i = 17;
        localObject1 = arrayOfString;
        break;
      case 17: 
        localObject3[i4] = localObject1;
        j = 19;
        localObject2 = "QMxO$m\023R\022";
        i = 18;
        localObject1 = arrayOfString;
        break;
      case 18: 
        localObject3[i4] = localObject1;
        j = 20;
        localObject2 = "QMxO$m\022R\020";
        i = 19;
        localObject1 = arrayOfString;
        break;
      case 19: 
        localObject3[i4] = localObject1;
        j = 21;
        localObject2 = "AMU\017YGt\033";
        i = 20;
        localObject1 = arrayOfString;
        break;
      case 20: 
        localObject3[i4] = localObject1;
        j = 22;
        localObject2 = "AVlU9AVdB#zGaQ5@";
        i = 21;
        localObject1 = arrayOfString;
        break;
      case 21: 
        localObject3[i4] = localObject1;
        j = 23;
        localObject2 = "|GW5@\002}D\"TML5V\003,\000paVlU9AVdB#v`I@$S\002dRp\\WaM";
        i = 22;
        localObject1 = arrayOfString;
        break;
      case 22: 
        localObject3[i4] = localObject1;
        j = 24;
        localObject2 = "\022K~\0015JK~U#\022\030-T VCyD";
        i = 23;
        localObject1 = arrayOfString;
        break;
      case 23: 
        localObject3[i4] = localObject1;
        j = 25;
        localObject2 = "\022LbUpWZdR$A\0027\0019\\QhS$";
        i = 24;
        localObject1 = arrayOfString;
        break;
      case 24: 
        localObject3[i4] = localObject1;
        j = 26;
        localObject2 = "AMU\017YGt\001j\022";
        i = 25;
        localObject1 = arrayOfString;
        break;
      case 25: 
        localObject3[i4] = localObject1;
        j = 27;
        localObject2 = "|GW5@\002}D\"TML5V\003,\000pQWR?@\002dRp\\WaM";
        i = 26;
        localObject1 = arrayOfString;
        break;
      case 26: 
        localObject3[i4] = localObject1;
        j = 28;
        localObject2 = "\022\002-\001<]EdO\017QM~U9_G7\001";
        i = 27;
        localObject1 = arrayOfString;
        break;
      case 27: 
        localObject3[i4] = localObject1;
        z = arrayOfString;
        return;
        i = 50;
        continue;
        i = 34;
        continue;
        i = 13;
        continue;
        i = 33;
      }
    }
  }
  
  private static JSONObject a(e parame)
  {
    JSONObject localJSONObject1 = new JSONObject();
    try
    {
      localJSONObject1.put(z[4], parame.b());
      localJSONObject1.put(z[3], parame.c());
      localJSONObject1.put(z[1], parame.d());
      localJSONObject1.put(z[0], parame.e());
      localJSONObject1.put(z[2], parame.g());
      JSONObject localJSONObject2 = new JSONObject();
      localJSONObject2.put(z[20], parame.h());
      localJSONObject2.put(z[19], parame.i());
      localJSONObject2.put(z[18], parame.j());
      localJSONObject1.put(z[17], localJSONObject2);
      return localJSONObject1;
    }
    catch (JSONException parame)
    {
      parame.printStackTrace();
    }
    return localJSONObject1;
  }
  
  public static void a(Context paramContext)
  {
    if (paramContext == null) {
      return;
    }
    b(paramContext);
    c(paramContext);
  }
  
  /* Error */
  public static void a(Context paramContext, int paramInt1, long paramLong, int paramInt2)
  {
    // Byte code:
    //   0: ldc 2
    //   2: monitorenter
    //   3: getstatic 82	cn/jiguang/c/f/c:z	[Ljava/lang/String;
    //   6: bipush 16
    //   8: aaload
    //   9: getstatic 82	cn/jiguang/c/f/c:z	[Ljava/lang/String;
    //   12: bipush 22
    //   14: aaload
    //   15: invokestatic 141	cn/jiguang/d/d:e	(Ljava/lang/String;Ljava/lang/String;)V
    //   18: aload_0
    //   19: invokestatic 146	cn/jiguang/f/j:a	(Landroid/content/Context;)Ljava/lang/String;
    //   22: astore 14
    //   24: invokestatic 149	cn/jiguang/c/a/a:c	()Ljava/lang/String;
    //   27: ifnonnull +174 -> 201
    //   30: ldc -105
    //   32: astore 12
    //   34: new 153	java/lang/StringBuilder
    //   37: dup
    //   38: invokespecial 154	java/lang/StringBuilder:<init>	()V
    //   41: aload 14
    //   43: invokevirtual 158	java/lang/StringBuilder:append	(Ljava/lang/String;)Ljava/lang/StringBuilder;
    //   46: ldc -96
    //   48: invokevirtual 158	java/lang/StringBuilder:append	(Ljava/lang/String;)Ljava/lang/StringBuilder;
    //   51: iload_1
    //   52: invokevirtual 163	java/lang/StringBuilder:append	(I)Ljava/lang/StringBuilder;
    //   55: ldc -96
    //   57: invokevirtual 158	java/lang/StringBuilder:append	(Ljava/lang/String;)Ljava/lang/StringBuilder;
    //   60: aload 12
    //   62: invokevirtual 158	java/lang/StringBuilder:append	(Ljava/lang/String;)Ljava/lang/StringBuilder;
    //   65: ldc -96
    //   67: invokevirtual 158	java/lang/StringBuilder:append	(Ljava/lang/String;)Ljava/lang/StringBuilder;
    //   70: invokestatic 166	cn/jiguang/f/a:c	()Ljava/lang/String;
    //   73: invokevirtual 158	java/lang/StringBuilder:append	(Ljava/lang/String;)Ljava/lang/StringBuilder;
    //   76: invokevirtual 169	java/lang/StringBuilder:toString	()Ljava/lang/String;
    //   79: astore 15
    //   81: getstatic 82	cn/jiguang/c/f/c:z	[Ljava/lang/String;
    //   84: bipush 16
    //   86: aaload
    //   87: new 153	java/lang/StringBuilder
    //   90: dup
    //   91: getstatic 82	cn/jiguang/c/f/c:z	[Ljava/lang/String;
    //   94: bipush 26
    //   96: aaload
    //   97: invokespecial 172	java/lang/StringBuilder:<init>	(Ljava/lang/String;)V
    //   100: aload 15
    //   102: invokevirtual 158	java/lang/StringBuilder:append	(Ljava/lang/String;)Ljava/lang/StringBuilder;
    //   105: getstatic 82	cn/jiguang/c/f/c:z	[Ljava/lang/String;
    //   108: bipush 28
    //   110: aaload
    //   111: invokevirtual 158	java/lang/StringBuilder:append	(Ljava/lang/String;)Ljava/lang/StringBuilder;
    //   114: lload_2
    //   115: invokevirtual 175	java/lang/StringBuilder:append	(J)Ljava/lang/StringBuilder;
    //   118: invokevirtual 169	java/lang/StringBuilder:toString	()Ljava/lang/String;
    //   121: invokestatic 177	cn/jiguang/d/d:c	(Ljava/lang/String;Ljava/lang/String;)V
    //   124: iconst_0
    //   125: istore 5
    //   127: iconst_0
    //   128: istore 7
    //   130: iconst_0
    //   131: istore 11
    //   133: iconst_0
    //   134: istore 8
    //   136: iconst_0
    //   137: istore 10
    //   139: iload 10
    //   141: istore 9
    //   143: iload 4
    //   145: ifne +17 -> 162
    //   148: lload_2
    //   149: ldc2_w 178
    //   152: lcmp
    //   153: ifgt +382 -> 535
    //   156: iconst_1
    //   157: istore 5
    //   159: goto +376 -> 535
    //   162: aload_0
    //   163: invokestatic 184	cn/jiguang/c/a/c:a	(Landroid/content/Context;)Lcn/jiguang/c/a/c;
    //   166: astore 13
    //   168: aload 13
    //   170: ifnull +27 -> 197
    //   173: aload 13
    //   175: iconst_1
    //   176: invokevirtual 187	cn/jiguang/c/a/c:a	(Z)Z
    //   179: ifne +30 -> 209
    //   182: getstatic 82	cn/jiguang/c/f/c:z	[Ljava/lang/String;
    //   185: bipush 16
    //   187: aaload
    //   188: getstatic 82	cn/jiguang/c/f/c:z	[Ljava/lang/String;
    //   191: bipush 14
    //   193: aaload
    //   194: invokestatic 189	cn/jiguang/d/d:i	(Ljava/lang/String;Ljava/lang/String;)V
    //   197: ldc 2
    //   199: monitorexit
    //   200: return
    //   201: invokestatic 149	cn/jiguang/c/a/a:c	()Ljava/lang/String;
    //   204: astore 12
    //   206: goto -172 -> 34
    //   209: aload 13
    //   211: aload 15
    //   213: invokevirtual 192	cn/jiguang/c/a/c:a	(Ljava/lang/String;)Z
    //   216: ifeq +227 -> 443
    //   219: getstatic 82	cn/jiguang/c/f/c:z	[Ljava/lang/String;
    //   222: bipush 16
    //   224: aaload
    //   225: new 153	java/lang/StringBuilder
    //   228: dup
    //   229: getstatic 82	cn/jiguang/c/f/c:z	[Ljava/lang/String;
    //   232: bipush 21
    //   234: aaload
    //   235: invokespecial 172	java/lang/StringBuilder:<init>	(Ljava/lang/String;)V
    //   238: aload 15
    //   240: invokevirtual 158	java/lang/StringBuilder:append	(Ljava/lang/String;)Ljava/lang/StringBuilder;
    //   243: getstatic 82	cn/jiguang/c/f/c:z	[Ljava/lang/String;
    //   246: bipush 24
    //   248: aaload
    //   249: invokevirtual 158	java/lang/StringBuilder:append	(Ljava/lang/String;)Ljava/lang/StringBuilder;
    //   252: invokevirtual 169	java/lang/StringBuilder:toString	()Ljava/lang/String;
    //   255: invokestatic 141	cn/jiguang/d/d:e	(Ljava/lang/String;Ljava/lang/String;)V
    //   258: aload 13
    //   260: aload 15
    //   262: invokevirtual 195	cn/jiguang/c/a/c:b	(Ljava/lang/String;)Landroid/database/Cursor;
    //   265: astore_0
    //   266: aload_0
    //   267: ifnonnull +18 -> 285
    //   270: getstatic 82	cn/jiguang/c/f/c:z	[Ljava/lang/String;
    //   273: bipush 16
    //   275: aaload
    //   276: getstatic 82	cn/jiguang/c/f/c:z	[Ljava/lang/String;
    //   279: bipush 27
    //   281: aaload
    //   282: invokestatic 197	cn/jiguang/d/d:g	(Ljava/lang/String;Ljava/lang/String;)V
    //   285: aload 13
    //   287: aload_0
    //   288: invokevirtual 200	cn/jiguang/c/a/c:a	(Landroid/database/Cursor;)Lcn/jiguang/c/a/e;
    //   291: astore 16
    //   293: aload 16
    //   295: ifnull +102 -> 397
    //   298: aload 13
    //   300: aload 15
    //   302: aload 14
    //   304: aload 12
    //   306: invokestatic 166	cn/jiguang/f/a:c	()Ljava/lang/String;
    //   309: new 153	java/lang/StringBuilder
    //   312: dup
    //   313: invokespecial 154	java/lang/StringBuilder:<init>	()V
    //   316: iload_1
    //   317: invokevirtual 163	java/lang/StringBuilder:append	(I)Ljava/lang/StringBuilder;
    //   320: invokevirtual 169	java/lang/StringBuilder:toString	()Ljava/lang/String;
    //   323: aload 16
    //   325: invokevirtual 203	cn/jiguang/c/a/e:f	()I
    //   328: iload 4
    //   330: iadd
    //   331: aload 16
    //   333: invokevirtual 113	cn/jiguang/c/a/e:g	()I
    //   336: iconst_1
    //   337: iadd
    //   338: iload 7
    //   340: aload 16
    //   342: invokevirtual 119	cn/jiguang/c/a/e:h	()I
    //   345: iadd
    //   346: iload 8
    //   348: aload 16
    //   350: invokevirtual 122	cn/jiguang/c/a/e:i	()I
    //   353: iadd
    //   354: iload 9
    //   356: aload 16
    //   358: invokevirtual 125	cn/jiguang/c/a/e:j	()I
    //   361: iadd
    //   362: aload 16
    //   364: invokevirtual 206	cn/jiguang/c/a/e:k	()I
    //   367: iconst_0
    //   368: iadd
    //   369: invokevirtual 209	cn/jiguang/c/a/c:b	(Ljava/lang/String;Ljava/lang/String;Ljava/lang/String;Ljava/lang/String;Ljava/lang/String;IIIIII)Z
    //   372: pop
    //   373: aload_0
    //   374: ifnull +9 -> 383
    //   377: aload_0
    //   378: invokeinterface 214 1 0
    //   383: aload 13
    //   385: invokevirtual 216	cn/jiguang/c/a/c:a	()V
    //   388: goto -191 -> 197
    //   391: astore_0
    //   392: ldc 2
    //   394: monitorexit
    //   395: aload_0
    //   396: athrow
    //   397: getstatic 82	cn/jiguang/c/f/c:z	[Ljava/lang/String;
    //   400: bipush 16
    //   402: aaload
    //   403: getstatic 82	cn/jiguang/c/f/c:z	[Ljava/lang/String;
    //   406: bipush 23
    //   408: aaload
    //   409: invokestatic 197	cn/jiguang/d/d:g	(Ljava/lang/String;Ljava/lang/String;)V
    //   412: goto -39 -> 373
    //   415: astore 12
    //   417: aload_0
    //   418: ifnull -35 -> 383
    //   421: aload_0
    //   422: invokeinterface 214 1 0
    //   427: goto -44 -> 383
    //   430: aload_0
    //   431: ifnull +9 -> 440
    //   434: aload_0
    //   435: invokeinterface 214 1 0
    //   440: aload 12
    //   442: athrow
    //   443: getstatic 82	cn/jiguang/c/f/c:z	[Ljava/lang/String;
    //   446: bipush 16
    //   448: aaload
    //   449: new 153	java/lang/StringBuilder
    //   452: dup
    //   453: getstatic 82	cn/jiguang/c/f/c:z	[Ljava/lang/String;
    //   456: bipush 21
    //   458: aaload
    //   459: invokespecial 172	java/lang/StringBuilder:<init>	(Ljava/lang/String;)V
    //   462: aload 15
    //   464: invokevirtual 158	java/lang/StringBuilder:append	(Ljava/lang/String;)Ljava/lang/StringBuilder;
    //   467: getstatic 82	cn/jiguang/c/f/c:z	[Ljava/lang/String;
    //   470: bipush 25
    //   472: aaload
    //   473: invokevirtual 158	java/lang/StringBuilder:append	(Ljava/lang/String;)Ljava/lang/StringBuilder;
    //   476: invokevirtual 169	java/lang/StringBuilder:toString	()Ljava/lang/String;
    //   479: invokestatic 141	cn/jiguang/d/d:e	(Ljava/lang/String;Ljava/lang/String;)V
    //   482: aload 13
    //   484: aload 15
    //   486: aload 14
    //   488: aload 12
    //   490: invokestatic 166	cn/jiguang/f/a:c	()Ljava/lang/String;
    //   493: new 153	java/lang/StringBuilder
    //   496: dup
    //   497: invokespecial 154	java/lang/StringBuilder:<init>	()V
    //   500: iload_1
    //   501: invokevirtual 163	java/lang/StringBuilder:append	(I)Ljava/lang/StringBuilder;
    //   504: invokevirtual 169	java/lang/StringBuilder:toString	()Ljava/lang/String;
    //   507: iload 4
    //   509: iconst_1
    //   510: iload 7
    //   512: iload 8
    //   514: iload 9
    //   516: iconst_0
    //   517: invokevirtual 219	cn/jiguang/c/a/c:a	(Ljava/lang/String;Ljava/lang/String;Ljava/lang/String;Ljava/lang/String;Ljava/lang/String;IIIIII)J
    //   520: pop2
    //   521: goto -138 -> 383
    //   524: astore 12
    //   526: goto -96 -> 430
    //   529: astore_0
    //   530: aconst_null
    //   531: astore_0
    //   532: goto -115 -> 417
    //   535: iload 11
    //   537: istore 6
    //   539: lload_2
    //   540: ldc2_w 178
    //   543: lcmp
    //   544: ifle +18 -> 562
    //   547: iload 11
    //   549: istore 6
    //   551: lload_2
    //   552: ldc2_w 220
    //   555: lcmp
    //   556: ifgt +6 -> 562
    //   559: iconst_1
    //   560: istore 6
    //   562: iload 5
    //   564: istore 7
    //   566: iload 6
    //   568: istore 8
    //   570: iload 10
    //   572: istore 9
    //   574: lload_2
    //   575: ldc2_w 220
    //   578: lcmp
    //   579: ifle -417 -> 162
    //   582: iconst_1
    //   583: istore 9
    //   585: iload 5
    //   587: istore 7
    //   589: iload 6
    //   591: istore 8
    //   593: goto -431 -> 162
    //   596: astore 12
    //   598: aconst_null
    //   599: astore_0
    //   600: goto -170 -> 430
    // Local variable table:
    //   start	length	slot	name	signature
    //   0	603	0	paramContext	Context
    //   0	603	1	paramInt1	int
    //   0	603	2	paramLong	long
    //   0	603	4	paramInt2	int
    //   125	461	5	i	int
    //   537	53	6	j	int
    //   128	460	7	k	int
    //   134	458	8	m	int
    //   141	443	9	n	int
    //   137	434	10	i1	int
    //   131	417	11	i2	int
    //   32	273	12	str1	String
    //   415	74	12	localException	Exception
    //   524	1	12	localObject1	Object
    //   596	1	12	localObject2	Object
    //   166	317	13	localc	cn.jiguang.c.a.c
    //   22	465	14	str2	String
    //   79	406	15	str3	String
    //   291	72	16	locale	e
    // Exception table:
    //   from	to	target	type
    //   3	30	391	finally
    //   34	124	391	finally
    //   162	168	391	finally
    //   173	197	391	finally
    //   201	206	391	finally
    //   209	258	391	finally
    //   377	383	391	finally
    //   383	388	391	finally
    //   421	427	391	finally
    //   434	440	391	finally
    //   440	443	391	finally
    //   443	521	391	finally
    //   270	285	415	java/lang/Exception
    //   285	293	415	java/lang/Exception
    //   298	373	415	java/lang/Exception
    //   397	412	415	java/lang/Exception
    //   270	285	524	finally
    //   285	293	524	finally
    //   298	373	524	finally
    //   397	412	524	finally
    //   258	266	529	java/lang/Exception
    //   258	266	596	finally
  }
  
  private static JSONObject b(e parame)
  {
    JSONObject localJSONObject = new JSONObject();
    try
    {
      localJSONObject.put(z[4], parame.b());
      localJSONObject.put(z[3], parame.c());
      localJSONObject.put(z[1], parame.d());
      localJSONObject.put(z[0], parame.e());
      localJSONObject.put(z[2], parame.g());
      return localJSONObject;
    }
    catch (JSONException parame)
    {
      parame.printStackTrace();
    }
    return localJSONObject;
  }
  
  /* Error */
  private static void b(Context paramContext)
  {
    // Byte code:
    //   0: aconst_null
    //   1: astore 7
    //   3: aconst_null
    //   4: astore 8
    //   6: aconst_null
    //   7: astore 6
    //   9: ldc 2
    //   11: monitorenter
    //   12: invokestatic 225	cn/jiguang/c/a/a:s	()Z
    //   15: istore_1
    //   16: iload_1
    //   17: ifne +7 -> 24
    //   20: ldc 2
    //   22: monitorexit
    //   23: return
    //   24: new 89	org/json/JSONObject
    //   27: dup
    //   28: invokespecial 91	org/json/JSONObject:<init>	()V
    //   31: astore 10
    //   33: aload_0
    //   34: invokestatic 184	cn/jiguang/c/a/c:a	(Landroid/content/Context;)Lcn/jiguang/c/a/c;
    //   37: astore 9
    //   39: aload 6
    //   41: astore_3
    //   42: aload 7
    //   44: astore 5
    //   46: aload 8
    //   48: astore_2
    //   49: aload 10
    //   51: getstatic 82	cn/jiguang/c/f/c:z	[Ljava/lang/String;
    //   54: bipush 13
    //   56: aaload
    //   57: invokestatic 228	cn/jiguang/c/a/a:g	()J
    //   60: invokevirtual 231	org/json/JSONObject:put	(Ljava/lang/String;J)Lorg/json/JSONObject;
    //   63: pop
    //   64: aload 6
    //   66: astore_3
    //   67: aload 7
    //   69: astore 5
    //   71: aload 8
    //   73: astore_2
    //   74: aload 10
    //   76: getstatic 82	cn/jiguang/c/f/c:z	[Ljava/lang/String;
    //   79: bipush 12
    //   81: aaload
    //   82: getstatic 82	cn/jiguang/c/f/c:z	[Ljava/lang/String;
    //   85: bipush 10
    //   87: aaload
    //   88: invokevirtual 100	org/json/JSONObject:put	(Ljava/lang/String;Ljava/lang/Object;)Lorg/json/JSONObject;
    //   91: pop
    //   92: aload 6
    //   94: astore_3
    //   95: aload 7
    //   97: astore 5
    //   99: aload 8
    //   101: astore_2
    //   102: aload 10
    //   104: getstatic 82	cn/jiguang/c/f/c:z	[Ljava/lang/String;
    //   107: iconst_5
    //   108: aaload
    //   109: new 233	java/text/SimpleDateFormat
    //   112: dup
    //   113: getstatic 82	cn/jiguang/c/f/c:z	[Ljava/lang/String;
    //   116: bipush 6
    //   118: aaload
    //   119: invokespecial 234	java/text/SimpleDateFormat:<init>	(Ljava/lang/String;)V
    //   122: new 236	java/util/Date
    //   125: dup
    //   126: invokestatic 238	cn/jiguang/c/a/a:b	()J
    //   129: invokespecial 241	java/util/Date:<init>	(J)V
    //   132: invokevirtual 245	java/text/SimpleDateFormat:format	(Ljava/util/Date;)Ljava/lang/String;
    //   135: invokevirtual 100	org/json/JSONObject:put	(Ljava/lang/String;Ljava/lang/Object;)Lorg/json/JSONObject;
    //   138: pop
    //   139: aload 6
    //   141: astore_3
    //   142: aload 7
    //   144: astore 5
    //   146: aload 8
    //   148: astore_2
    //   149: aload 9
    //   151: iconst_0
    //   152: invokevirtual 187	cn/jiguang/c/a/c:a	(Z)Z
    //   155: ifne +47 -> 202
    //   158: aload 6
    //   160: astore_3
    //   161: aload 7
    //   163: astore 5
    //   165: aload 8
    //   167: astore_2
    //   168: getstatic 82	cn/jiguang/c/f/c:z	[Ljava/lang/String;
    //   171: bipush 16
    //   173: aaload
    //   174: getstatic 82	cn/jiguang/c/f/c:z	[Ljava/lang/String;
    //   177: bipush 14
    //   179: aaload
    //   180: invokestatic 189	cn/jiguang/d/d:i	(Ljava/lang/String;Ljava/lang/String;)V
    //   183: aload 9
    //   185: ifnull -165 -> 20
    //   188: aload 9
    //   190: invokevirtual 216	cn/jiguang/c/a/c:a	()V
    //   193: goto -173 -> 20
    //   196: astore_0
    //   197: ldc 2
    //   199: monitorexit
    //   200: aload_0
    //   201: athrow
    //   202: aload 6
    //   204: astore_3
    //   205: aload 7
    //   207: astore 5
    //   209: aload 8
    //   211: astore_2
    //   212: aload 10
    //   214: getstatic 82	cn/jiguang/c/f/c:z	[Ljava/lang/String;
    //   217: bipush 15
    //   219: aaload
    //   220: aload 9
    //   222: iconst_1
    //   223: invokevirtual 248	cn/jiguang/c/a/c:b	(Z)I
    //   226: invokevirtual 116	org/json/JSONObject:put	(Ljava/lang/String;I)Lorg/json/JSONObject;
    //   229: pop
    //   230: aload 6
    //   232: astore_3
    //   233: aload 7
    //   235: astore 5
    //   237: aload 8
    //   239: astore_2
    //   240: aload 10
    //   242: getstatic 82	cn/jiguang/c/f/c:z	[Ljava/lang/String;
    //   245: bipush 11
    //   247: aaload
    //   248: aload 9
    //   250: iconst_0
    //   251: invokevirtual 248	cn/jiguang/c/a/c:b	(Z)I
    //   254: invokevirtual 116	org/json/JSONObject:put	(Ljava/lang/String;I)Lorg/json/JSONObject;
    //   257: pop
    //   258: aload 6
    //   260: astore_3
    //   261: aload 7
    //   263: astore 5
    //   265: aload 8
    //   267: astore_2
    //   268: new 250	org/json/JSONArray
    //   271: dup
    //   272: invokespecial 251	org/json/JSONArray:<init>	()V
    //   275: astore 11
    //   277: aload 6
    //   279: astore_3
    //   280: aload 7
    //   282: astore 5
    //   284: aload 8
    //   286: astore_2
    //   287: aload 9
    //   289: invokevirtual 254	cn/jiguang/c/a/c:c	()Landroid/database/Cursor;
    //   292: astore 4
    //   294: aload 4
    //   296: ifnull +57 -> 353
    //   299: aload 9
    //   301: aload 4
    //   303: invokevirtual 200	cn/jiguang/c/a/c:a	(Landroid/database/Cursor;)Lcn/jiguang/c/a/e;
    //   306: astore_2
    //   307: aload_2
    //   308: ifnull +13 -> 321
    //   311: aload_2
    //   312: invokevirtual 256	cn/jiguang/c/a/e:a	()Ljava/lang/String;
    //   315: invokestatic 259	cn/jiguang/f/h:a	(Ljava/lang/String;)Z
    //   318: ifeq +277 -> 595
    //   321: getstatic 82	cn/jiguang/c/f/c:z	[Ljava/lang/String;
    //   324: bipush 16
    //   326: aaload
    //   327: getstatic 82	cn/jiguang/c/f/c:z	[Ljava/lang/String;
    //   330: bipush 9
    //   332: aaload
    //   333: invokestatic 177	cn/jiguang/d/d:c	(Ljava/lang/String;Ljava/lang/String;)V
    //   336: aload 4
    //   338: invokeinterface 262 1 0
    //   343: ifne -44 -> 299
    //   346: aload 4
    //   348: invokeinterface 214 1 0
    //   353: aload 10
    //   355: getstatic 82	cn/jiguang/c/f/c:z	[Ljava/lang/String;
    //   358: bipush 8
    //   360: aaload
    //   361: aload 11
    //   363: invokevirtual 100	org/json/JSONObject:put	(Ljava/lang/String;Ljava/lang/Object;)Lorg/json/JSONObject;
    //   366: pop
    //   367: aload 6
    //   369: astore_3
    //   370: aload 7
    //   372: astore 5
    //   374: aload 8
    //   376: astore_2
    //   377: new 250	org/json/JSONArray
    //   380: dup
    //   381: invokespecial 251	org/json/JSONArray:<init>	()V
    //   384: astore 11
    //   386: aload 6
    //   388: astore_3
    //   389: aload 7
    //   391: astore 5
    //   393: aload 8
    //   395: astore_2
    //   396: aload 9
    //   398: invokevirtual 264	cn/jiguang/c/a/c:d	()Landroid/database/Cursor;
    //   401: astore 4
    //   403: aload 4
    //   405: ifnull +110 -> 515
    //   408: aload 4
    //   410: astore_3
    //   411: aload 4
    //   413: astore 5
    //   415: aload 4
    //   417: astore_2
    //   418: aload 9
    //   420: aload 4
    //   422: invokevirtual 200	cn/jiguang/c/a/c:a	(Landroid/database/Cursor;)Lcn/jiguang/c/a/e;
    //   425: astore 6
    //   427: aload 6
    //   429: ifnull +24 -> 453
    //   432: aload 4
    //   434: astore_3
    //   435: aload 4
    //   437: astore 5
    //   439: aload 4
    //   441: astore_2
    //   442: aload 6
    //   444: invokevirtual 256	cn/jiguang/c/a/e:a	()Ljava/lang/String;
    //   447: invokestatic 259	cn/jiguang/f/h:a	(Ljava/lang/String;)Z
    //   450: ifeq +204 -> 654
    //   453: aload 4
    //   455: astore_3
    //   456: aload 4
    //   458: astore 5
    //   460: aload 4
    //   462: astore_2
    //   463: getstatic 82	cn/jiguang/c/f/c:z	[Ljava/lang/String;
    //   466: bipush 16
    //   468: aaload
    //   469: getstatic 82	cn/jiguang/c/f/c:z	[Ljava/lang/String;
    //   472: bipush 9
    //   474: aaload
    //   475: invokestatic 177	cn/jiguang/d/d:c	(Ljava/lang/String;Ljava/lang/String;)V
    //   478: aload 4
    //   480: astore_3
    //   481: aload 4
    //   483: astore 5
    //   485: aload 4
    //   487: astore_2
    //   488: aload 4
    //   490: invokeinterface 262 1 0
    //   495: ifne -87 -> 408
    //   498: aload 4
    //   500: astore_3
    //   501: aload 4
    //   503: astore 5
    //   505: aload 4
    //   507: astore_2
    //   508: aload 4
    //   510: invokeinterface 214 1 0
    //   515: aload 4
    //   517: astore_3
    //   518: aload 4
    //   520: astore 5
    //   522: aload 4
    //   524: astore_2
    //   525: aload 10
    //   527: getstatic 82	cn/jiguang/c/f/c:z	[Ljava/lang/String;
    //   530: bipush 7
    //   532: aaload
    //   533: aload 11
    //   535: invokevirtual 100	org/json/JSONObject:put	(Ljava/lang/String;Ljava/lang/Object;)Lorg/json/JSONObject;
    //   538: pop
    //   539: aload 4
    //   541: astore_3
    //   542: aload 4
    //   544: astore 5
    //   546: aload 4
    //   548: astore_2
    //   549: aload 9
    //   551: invokevirtual 216	cn/jiguang/c/a/c:a	()V
    //   554: aload 4
    //   556: astore_3
    //   557: aload 4
    //   559: astore 5
    //   561: aload 4
    //   563: astore_2
    //   564: aload_0
    //   565: aload 10
    //   567: invokestatic 269	cn/jiguang/c/d/l:a	(Landroid/content/Context;Lorg/json/JSONObject;)V
    //   570: aload 4
    //   572: ifnull +10 -> 582
    //   575: aload 4
    //   577: invokeinterface 214 1 0
    //   582: aload 9
    //   584: ifnull -564 -> 20
    //   587: aload 9
    //   589: invokevirtual 216	cn/jiguang/c/a/c:a	()V
    //   592: goto -572 -> 20
    //   595: aload 11
    //   597: aload_2
    //   598: invokestatic 271	cn/jiguang/c/f/c:b	(Lcn/jiguang/c/a/e;)Lorg/json/JSONObject;
    //   601: invokevirtual 274	org/json/JSONArray:put	(Ljava/lang/Object;)Lorg/json/JSONArray;
    //   604: pop
    //   605: goto -269 -> 336
    //   608: astore_0
    //   609: aload 4
    //   611: astore_3
    //   612: aload_3
    //   613: astore_2
    //   614: getstatic 82	cn/jiguang/c/f/c:z	[Ljava/lang/String;
    //   617: bipush 16
    //   619: aaload
    //   620: ldc -105
    //   622: invokestatic 189	cn/jiguang/d/d:i	(Ljava/lang/String;Ljava/lang/String;)V
    //   625: aload_3
    //   626: astore_2
    //   627: aload_0
    //   628: invokevirtual 128	org/json/JSONException:printStackTrace	()V
    //   631: aload_3
    //   632: ifnull +9 -> 641
    //   635: aload_3
    //   636: invokeinterface 214 1 0
    //   641: aload 9
    //   643: ifnull -623 -> 20
    //   646: aload 9
    //   648: invokevirtual 216	cn/jiguang/c/a/c:a	()V
    //   651: goto -631 -> 20
    //   654: aload 4
    //   656: astore_3
    //   657: aload 4
    //   659: astore 5
    //   661: aload 4
    //   663: astore_2
    //   664: aload 11
    //   666: aload 6
    //   668: invokestatic 276	cn/jiguang/c/f/c:a	(Lcn/jiguang/c/a/e;)Lorg/json/JSONObject;
    //   671: invokevirtual 274	org/json/JSONArray:put	(Ljava/lang/Object;)Lorg/json/JSONArray;
    //   674: pop
    //   675: goto -197 -> 478
    //   678: astore_0
    //   679: goto -67 -> 612
    //   682: astore_0
    //   683: aload 5
    //   685: astore_2
    //   686: getstatic 82	cn/jiguang/c/f/c:z	[Ljava/lang/String;
    //   689: bipush 16
    //   691: aaload
    //   692: ldc -105
    //   694: invokestatic 189	cn/jiguang/d/d:i	(Ljava/lang/String;Ljava/lang/String;)V
    //   697: aload 5
    //   699: astore_2
    //   700: aload_0
    //   701: invokevirtual 277	java/lang/Exception:printStackTrace	()V
    //   704: aload 5
    //   706: ifnull +10 -> 716
    //   709: aload 5
    //   711: invokeinterface 214 1 0
    //   716: aload 9
    //   718: ifnull -698 -> 20
    //   721: aload 9
    //   723: invokevirtual 216	cn/jiguang/c/a/c:a	()V
    //   726: goto -706 -> 20
    //   729: aload_2
    //   730: ifnull +9 -> 739
    //   733: aload_2
    //   734: invokeinterface 214 1 0
    //   739: aload 9
    //   741: ifnull +8 -> 749
    //   744: aload 9
    //   746: invokevirtual 216	cn/jiguang/c/a/c:a	()V
    //   749: aload_0
    //   750: athrow
    //   751: astore_0
    //   752: aload 4
    //   754: astore_2
    //   755: goto -26 -> 729
    //   758: astore_0
    //   759: aload 4
    //   761: astore 5
    //   763: goto -80 -> 683
    //   766: astore_0
    //   767: goto -38 -> 729
    // Local variable table:
    //   start	length	slot	name	signature
    //   0	770	0	paramContext	Context
    //   15	2	1	bool	boolean
    //   48	707	2	localObject1	Object
    //   41	616	3	localObject2	Object
    //   292	468	4	localCursor	android.database.Cursor
    //   44	718	5	localObject3	Object
    //   7	660	6	locale	e
    //   1	389	7	localObject4	Object
    //   4	390	8	localObject5	Object
    //   37	708	9	localc	cn.jiguang.c.a.c
    //   31	535	10	localJSONObject	JSONObject
    //   275	390	11	localJSONArray	org.json.JSONArray
    // Exception table:
    //   from	to	target	type
    //   12	16	196	finally
    //   24	39	196	finally
    //   188	193	196	finally
    //   575	582	196	finally
    //   587	592	196	finally
    //   635	641	196	finally
    //   646	651	196	finally
    //   709	716	196	finally
    //   721	726	196	finally
    //   733	739	196	finally
    //   744	749	196	finally
    //   749	751	196	finally
    //   299	307	608	org/json/JSONException
    //   311	321	608	org/json/JSONException
    //   321	336	608	org/json/JSONException
    //   336	353	608	org/json/JSONException
    //   353	367	608	org/json/JSONException
    //   595	605	608	org/json/JSONException
    //   49	64	678	org/json/JSONException
    //   74	92	678	org/json/JSONException
    //   102	139	678	org/json/JSONException
    //   149	158	678	org/json/JSONException
    //   168	183	678	org/json/JSONException
    //   212	230	678	org/json/JSONException
    //   240	258	678	org/json/JSONException
    //   268	277	678	org/json/JSONException
    //   287	294	678	org/json/JSONException
    //   377	386	678	org/json/JSONException
    //   396	403	678	org/json/JSONException
    //   418	427	678	org/json/JSONException
    //   442	453	678	org/json/JSONException
    //   463	478	678	org/json/JSONException
    //   488	498	678	org/json/JSONException
    //   508	515	678	org/json/JSONException
    //   525	539	678	org/json/JSONException
    //   549	554	678	org/json/JSONException
    //   564	570	678	org/json/JSONException
    //   664	675	678	org/json/JSONException
    //   49	64	682	java/lang/Exception
    //   74	92	682	java/lang/Exception
    //   102	139	682	java/lang/Exception
    //   149	158	682	java/lang/Exception
    //   168	183	682	java/lang/Exception
    //   212	230	682	java/lang/Exception
    //   240	258	682	java/lang/Exception
    //   268	277	682	java/lang/Exception
    //   287	294	682	java/lang/Exception
    //   377	386	682	java/lang/Exception
    //   396	403	682	java/lang/Exception
    //   418	427	682	java/lang/Exception
    //   442	453	682	java/lang/Exception
    //   463	478	682	java/lang/Exception
    //   488	498	682	java/lang/Exception
    //   508	515	682	java/lang/Exception
    //   525	539	682	java/lang/Exception
    //   549	554	682	java/lang/Exception
    //   564	570	682	java/lang/Exception
    //   664	675	682	java/lang/Exception
    //   299	307	751	finally
    //   311	321	751	finally
    //   321	336	751	finally
    //   336	353	751	finally
    //   353	367	751	finally
    //   595	605	751	finally
    //   299	307	758	java/lang/Exception
    //   311	321	758	java/lang/Exception
    //   321	336	758	java/lang/Exception
    //   336	353	758	java/lang/Exception
    //   353	367	758	java/lang/Exception
    //   595	605	758	java/lang/Exception
    //   49	64	766	finally
    //   74	92	766	finally
    //   102	139	766	finally
    //   149	158	766	finally
    //   168	183	766	finally
    //   212	230	766	finally
    //   240	258	766	finally
    //   268	277	766	finally
    //   287	294	766	finally
    //   377	386	766	finally
    //   396	403	766	finally
    //   418	427	766	finally
    //   442	453	766	finally
    //   463	478	766	finally
    //   488	498	766	finally
    //   508	515	766	finally
    //   525	539	766	finally
    //   549	554	766	finally
    //   564	570	766	finally
    //   614	625	766	finally
    //   627	631	766	finally
    //   664	675	766	finally
    //   686	697	766	finally
    //   700	704	766	finally
  }
  
  private static void c(Context paramContext)
  {
    try
    {
      paramContext = cn.jiguang.c.a.c.a(paramContext);
      if (paramContext != null)
      {
        paramContext.a(true);
        paramContext.b();
        paramContext.a();
      }
      return;
    }
    finally {}
  }
}


/* Location:              /Users/gaoht/Downloads/zirom/classes-dex2jar.jar!/cn/jiguang/c/f/c.class
 * Java compiler version: 6 (50.0)
 * JD-Core Version:       0.7.1
 */