package com.baidu.trace;

import android.database.sqlite.SQLiteDatabase;

final class v
  implements Runnable
{
  v(u paramu, SQLiteDatabase paramSQLiteDatabase) {}
  
  /* Error */
  public final void run()
  {
    // Byte code:
    //   0: aload_0
    //   1: getfield 14	com/baidu/trace/v:b	Lcom/baidu/trace/u;
    //   4: invokestatic 28	com/baidu/trace/u:a	(Lcom/baidu/trace/u;)Landroid/database/sqlite/SQLiteOpenHelper;
    //   7: invokevirtual 34	android/database/sqlite/SQLiteOpenHelper:getWritableDatabase	()Landroid/database/sqlite/SQLiteDatabase;
    //   10: astore_3
    //   11: aload_3
    //   12: ldc 36
    //   14: aconst_null
    //   15: invokevirtual 42	android/database/sqlite/SQLiteDatabase:rawQuery	(Ljava/lang/String;[Ljava/lang/String;)Landroid/database/Cursor;
    //   18: astore 4
    //   20: aload 4
    //   22: ifnull +239 -> 261
    //   25: aload 4
    //   27: invokeinterface 48 1 0
    //   32: ifeq +229 -> 261
    //   35: aload 4
    //   37: aload 4
    //   39: ldc 50
    //   41: invokeinterface 54 2 0
    //   46: invokeinterface 58 2 0
    //   51: astore 6
    //   53: aload 6
    //   55: invokestatic 64	android/text/TextUtils:isEmpty	(Ljava/lang/CharSequence;)Z
    //   58: ifne -38 -> 20
    //   61: aload 6
    //   63: invokevirtual 70	java/lang/String:length	()I
    //   66: bipush 8
    //   68: if_icmplt -48 -> 20
    //   71: aload 6
    //   73: invokestatic 75	com/baidu/trace/c/d:a	(Ljava/lang/String;)[B
    //   76: astore 5
    //   78: aload 6
    //   80: aload 6
    //   82: invokevirtual 70	java/lang/String:length	()I
    //   85: bipush 8
    //   87: isub
    //   88: aload 6
    //   90: invokevirtual 70	java/lang/String:length	()I
    //   93: invokevirtual 79	java/lang/String:substring	(II)Ljava/lang/String;
    //   96: bipush 16
    //   98: invokestatic 85	java/lang/Long:parseLong	(Ljava/lang/String;I)J
    //   101: lstore_1
    //   102: new 87	java/lang/StringBuffer
    //   105: dup
    //   106: ldc 89
    //   108: invokespecial 92	java/lang/StringBuffer:<init>	(Ljava/lang/String;)V
    //   111: astore 6
    //   113: aload 6
    //   115: ldc 94
    //   117: invokevirtual 98	java/lang/StringBuffer:append	(Ljava/lang/String;)Ljava/lang/StringBuffer;
    //   120: ldc 100
    //   122: invokevirtual 98	java/lang/StringBuffer:append	(Ljava/lang/String;)Ljava/lang/StringBuffer;
    //   125: ldc 102
    //   127: invokevirtual 98	java/lang/StringBuffer:append	(Ljava/lang/String;)Ljava/lang/StringBuffer;
    //   130: ldc 104
    //   132: invokevirtual 98	java/lang/StringBuffer:append	(Ljava/lang/String;)Ljava/lang/StringBuffer;
    //   135: pop
    //   136: getstatic 110	com/baidu/trace/Trace:e	Ljava/lang/String;
    //   139: astore 7
    //   141: aload_0
    //   142: getfield 16	com/baidu/trace/v:a	Landroid/database/sqlite/SQLiteDatabase;
    //   145: aload 6
    //   147: invokevirtual 114	java/lang/StringBuffer:toString	()Ljava/lang/String;
    //   150: iconst_3
    //   151: anewarray 4	java/lang/Object
    //   154: dup
    //   155: iconst_0
    //   156: lload_1
    //   157: invokestatic 118	java/lang/Long:valueOf	(J)Ljava/lang/Long;
    //   160: aastore
    //   161: dup
    //   162: iconst_1
    //   163: aload 7
    //   165: aastore
    //   166: dup
    //   167: iconst_2
    //   168: aload 5
    //   170: aastore
    //   171: invokevirtual 122	android/database/sqlite/SQLiteDatabase:execSQL	(Ljava/lang/String;[Ljava/lang/Object;)V
    //   174: goto -154 -> 20
    //   177: astore 5
    //   179: aload 4
    //   181: ifnull +10 -> 191
    //   184: aload 4
    //   186: invokeinterface 125 1 0
    //   191: aload_3
    //   192: ifnull +7 -> 199
    //   195: aload_3
    //   196: invokevirtual 126	android/database/sqlite/SQLiteDatabase:close	()V
    //   199: aload_0
    //   200: getfield 14	com/baidu/trace/v:b	Lcom/baidu/trace/u;
    //   203: invokestatic 28	com/baidu/trace/u:a	(Lcom/baidu/trace/u;)Landroid/database/sqlite/SQLiteOpenHelper;
    //   206: ifnull +22 -> 228
    //   209: aload_0
    //   210: getfield 14	com/baidu/trace/v:b	Lcom/baidu/trace/u;
    //   213: invokestatic 28	com/baidu/trace/u:a	(Lcom/baidu/trace/u;)Landroid/database/sqlite/SQLiteOpenHelper;
    //   216: invokevirtual 127	android/database/sqlite/SQLiteOpenHelper:close	()V
    //   219: aload_0
    //   220: getfield 14	com/baidu/trace/v:b	Lcom/baidu/trace/u;
    //   223: aconst_null
    //   224: invokestatic 130	com/baidu/trace/u:a	(Lcom/baidu/trace/u;Landroid/database/sqlite/SQLiteOpenHelper;)Landroid/database/sqlite/SQLiteOpenHelper;
    //   227: pop
    //   228: aload_0
    //   229: getfield 14	com/baidu/trace/v:b	Lcom/baidu/trace/u;
    //   232: invokestatic 133	com/baidu/trace/u:b	(Lcom/baidu/trace/u;)Landroid/content/Context;
    //   235: ifnull +25 -> 260
    //   238: aload_0
    //   239: getfield 14	com/baidu/trace/v:b	Lcom/baidu/trace/u;
    //   242: invokestatic 133	com/baidu/trace/u:b	(Lcom/baidu/trace/u;)Landroid/content/Context;
    //   245: ldc -121
    //   247: invokevirtual 141	android/content/Context:deleteDatabase	(Ljava/lang/String;)Z
    //   250: pop
    //   251: aload_0
    //   252: getfield 14	com/baidu/trace/v:b	Lcom/baidu/trace/u;
    //   255: aconst_null
    //   256: invokestatic 144	com/baidu/trace/u:a	(Lcom/baidu/trace/u;Landroid/content/Context;)Landroid/content/Context;
    //   259: pop
    //   260: return
    //   261: aload 4
    //   263: ifnull +10 -> 273
    //   266: aload 4
    //   268: invokeinterface 125 1 0
    //   273: aload_3
    //   274: ifnull +7 -> 281
    //   277: aload_3
    //   278: invokevirtual 126	android/database/sqlite/SQLiteDatabase:close	()V
    //   281: aload_0
    //   282: getfield 14	com/baidu/trace/v:b	Lcom/baidu/trace/u;
    //   285: invokestatic 28	com/baidu/trace/u:a	(Lcom/baidu/trace/u;)Landroid/database/sqlite/SQLiteOpenHelper;
    //   288: ifnull +22 -> 310
    //   291: aload_0
    //   292: getfield 14	com/baidu/trace/v:b	Lcom/baidu/trace/u;
    //   295: invokestatic 28	com/baidu/trace/u:a	(Lcom/baidu/trace/u;)Landroid/database/sqlite/SQLiteOpenHelper;
    //   298: invokevirtual 127	android/database/sqlite/SQLiteOpenHelper:close	()V
    //   301: aload_0
    //   302: getfield 14	com/baidu/trace/v:b	Lcom/baidu/trace/u;
    //   305: aconst_null
    //   306: invokestatic 130	com/baidu/trace/u:a	(Lcom/baidu/trace/u;Landroid/database/sqlite/SQLiteOpenHelper;)Landroid/database/sqlite/SQLiteOpenHelper;
    //   309: pop
    //   310: aload_0
    //   311: getfield 14	com/baidu/trace/v:b	Lcom/baidu/trace/u;
    //   314: invokestatic 133	com/baidu/trace/u:b	(Lcom/baidu/trace/u;)Landroid/content/Context;
    //   317: ifnull -57 -> 260
    //   320: aload_0
    //   321: getfield 14	com/baidu/trace/v:b	Lcom/baidu/trace/u;
    //   324: invokestatic 133	com/baidu/trace/u:b	(Lcom/baidu/trace/u;)Landroid/content/Context;
    //   327: ldc -121
    //   329: invokevirtual 141	android/content/Context:deleteDatabase	(Ljava/lang/String;)Z
    //   332: pop
    //   333: aload_0
    //   334: getfield 14	com/baidu/trace/v:b	Lcom/baidu/trace/u;
    //   337: aconst_null
    //   338: invokestatic 144	com/baidu/trace/u:a	(Lcom/baidu/trace/u;Landroid/content/Context;)Landroid/content/Context;
    //   341: pop
    //   342: return
    //   343: astore_3
    //   344: aconst_null
    //   345: astore 4
    //   347: aconst_null
    //   348: astore 5
    //   350: aload 4
    //   352: ifnull +10 -> 362
    //   355: aload 4
    //   357: invokeinterface 125 1 0
    //   362: aload 5
    //   364: ifnull +8 -> 372
    //   367: aload 5
    //   369: invokevirtual 126	android/database/sqlite/SQLiteDatabase:close	()V
    //   372: aload_0
    //   373: getfield 14	com/baidu/trace/v:b	Lcom/baidu/trace/u;
    //   376: invokestatic 28	com/baidu/trace/u:a	(Lcom/baidu/trace/u;)Landroid/database/sqlite/SQLiteOpenHelper;
    //   379: ifnull +22 -> 401
    //   382: aload_0
    //   383: getfield 14	com/baidu/trace/v:b	Lcom/baidu/trace/u;
    //   386: invokestatic 28	com/baidu/trace/u:a	(Lcom/baidu/trace/u;)Landroid/database/sqlite/SQLiteOpenHelper;
    //   389: invokevirtual 127	android/database/sqlite/SQLiteOpenHelper:close	()V
    //   392: aload_0
    //   393: getfield 14	com/baidu/trace/v:b	Lcom/baidu/trace/u;
    //   396: aconst_null
    //   397: invokestatic 130	com/baidu/trace/u:a	(Lcom/baidu/trace/u;Landroid/database/sqlite/SQLiteOpenHelper;)Landroid/database/sqlite/SQLiteOpenHelper;
    //   400: pop
    //   401: aload_0
    //   402: getfield 14	com/baidu/trace/v:b	Lcom/baidu/trace/u;
    //   405: invokestatic 133	com/baidu/trace/u:b	(Lcom/baidu/trace/u;)Landroid/content/Context;
    //   408: ifnull +25 -> 433
    //   411: aload_0
    //   412: getfield 14	com/baidu/trace/v:b	Lcom/baidu/trace/u;
    //   415: invokestatic 133	com/baidu/trace/u:b	(Lcom/baidu/trace/u;)Landroid/content/Context;
    //   418: ldc -121
    //   420: invokevirtual 141	android/content/Context:deleteDatabase	(Ljava/lang/String;)Z
    //   423: pop
    //   424: aload_0
    //   425: getfield 14	com/baidu/trace/v:b	Lcom/baidu/trace/u;
    //   428: aconst_null
    //   429: invokestatic 144	com/baidu/trace/u:a	(Lcom/baidu/trace/u;Landroid/content/Context;)Landroid/content/Context;
    //   432: pop
    //   433: aload_3
    //   434: athrow
    //   435: astore 4
    //   437: aload_3
    //   438: astore 5
    //   440: aconst_null
    //   441: astore 6
    //   443: aload 4
    //   445: astore_3
    //   446: aload 6
    //   448: astore 4
    //   450: goto -100 -> 350
    //   453: astore 6
    //   455: aload_3
    //   456: astore 5
    //   458: aload 6
    //   460: astore_3
    //   461: goto -111 -> 350
    //   464: astore_3
    //   465: aconst_null
    //   466: astore 4
    //   468: aconst_null
    //   469: astore_3
    //   470: goto -291 -> 179
    //   473: astore 4
    //   475: aconst_null
    //   476: astore 4
    //   478: goto -299 -> 179
    // Local variable table:
    //   start	length	slot	name	signature
    //   0	481	0	this	v
    //   101	56	1	l	long
    //   10	268	3	localSQLiteDatabase	SQLiteDatabase
    //   343	95	3	localObject1	Object
    //   445	16	3	localObject2	Object
    //   464	1	3	localException1	Exception
    //   469	1	3	localObject3	Object
    //   18	338	4	localCursor	android.database.Cursor
    //   435	9	4	localObject4	Object
    //   448	19	4	localObject5	Object
    //   473	1	4	localException2	Exception
    //   476	1	4	localObject6	Object
    //   76	93	5	arrayOfByte	byte[]
    //   177	1	5	localException3	Exception
    //   348	109	5	localObject7	Object
    //   51	396	6	localObject8	Object
    //   453	6	6	localObject9	Object
    //   139	25	7	str	String
    // Exception table:
    //   from	to	target	type
    //   25	174	177	java/lang/Exception
    //   0	11	343	finally
    //   11	20	435	finally
    //   25	174	453	finally
    //   0	11	464	java/lang/Exception
    //   11	20	473	java/lang/Exception
  }
}


/* Location:              /Users/gaoht/Downloads/zirom/classes-dex2jar.jar!/com/baidu/trace/v.class
 * Java compiler version: 6 (50.0)
 * JD-Core Version:       0.7.1
 */