package com.alibaba.fastjson.parser.deserializer;

import com.alibaba.fastjson.parser.DefaultJSONParser;
import java.lang.reflect.Type;

public abstract class AbstractDateDeserializer
  extends ContextObjectDeserializer
  implements ObjectDeserializer
{
  protected abstract <T> T cast(DefaultJSONParser paramDefaultJSONParser, Type paramType, Object paramObject1, Object paramObject2);
  
  public <T> T deserialze(DefaultJSONParser paramDefaultJSONParser, Type paramType, Object paramObject)
  {
    return (T)deserialze(paramDefaultJSONParser, paramType, paramObject, null, 0);
  }
  
  /* Error */
  public <T> T deserialze(DefaultJSONParser paramDefaultJSONParser, Type paramType, Object paramObject, String paramString, int paramInt)
  {
    // Byte code:
    //   0: aconst_null
    //   1: astore 10
    //   3: aconst_null
    //   4: astore 8
    //   6: aload_1
    //   7: getfield 30	com/alibaba/fastjson/parser/DefaultJSONParser:lexer	Lcom/alibaba/fastjson/parser/JSONLexer;
    //   10: astore 11
    //   12: aload 11
    //   14: invokeinterface 36 1 0
    //   19: iconst_2
    //   20: if_icmpne +38 -> 58
    //   23: aload 11
    //   25: invokeinterface 40 1 0
    //   30: invokestatic 46	java/lang/Long:valueOf	(J)Ljava/lang/Long;
    //   33: astore 4
    //   35: aload 11
    //   37: bipush 16
    //   39: invokeinterface 50 2 0
    //   44: aload_2
    //   45: astore 10
    //   47: aload_0
    //   48: aload_1
    //   49: aload 10
    //   51: aload_3
    //   52: aload 4
    //   54: invokevirtual 52	com/alibaba/fastjson/parser/deserializer/AbstractDateDeserializer:cast	(Lcom/alibaba/fastjson/parser/DefaultJSONParser;Ljava/lang/reflect/Type;Ljava/lang/Object;Ljava/lang/Object;)Ljava/lang/Object;
    //   57: areturn
    //   58: aload 11
    //   60: invokeinterface 36 1 0
    //   65: iconst_4
    //   66: if_icmpne +222 -> 288
    //   69: aload 11
    //   71: invokeinterface 56 1 0
    //   76: astore 9
    //   78: aload 10
    //   80: astore 8
    //   82: aload 4
    //   84: ifnull +23 -> 107
    //   87: new 58	java/text/SimpleDateFormat
    //   90: dup
    //   91: aload 4
    //   93: invokespecial 61	java/text/SimpleDateFormat:<init>	(Ljava/lang/String;)V
    //   96: astore 8
    //   98: aload 8
    //   100: aload 9
    //   102: invokevirtual 65	java/text/SimpleDateFormat:parse	(Ljava/lang/String;)Ljava/util/Date;
    //   105: astore 8
    //   107: aload 8
    //   109: astore 4
    //   111: aload_2
    //   112: astore 10
    //   114: aload 8
    //   116: ifnonnull -69 -> 47
    //   119: aload 11
    //   121: bipush 16
    //   123: invokeinterface 50 2 0
    //   128: aload 11
    //   130: getstatic 71	com/alibaba/fastjson/parser/Feature:AllowISO8601DateFormat	Lcom/alibaba/fastjson/parser/Feature;
    //   133: invokeinterface 75 2 0
    //   138: ifeq +508 -> 646
    //   141: new 77	com/alibaba/fastjson/parser/JSONScanner
    //   144: dup
    //   145: aload 9
    //   147: invokespecial 78	com/alibaba/fastjson/parser/JSONScanner:<init>	(Ljava/lang/String;)V
    //   150: astore 8
    //   152: aload 8
    //   154: invokevirtual 82	com/alibaba/fastjson/parser/JSONScanner:scanISO8601DateIfMatch	()Z
    //   157: ifeq +482 -> 639
    //   160: aload 8
    //   162: invokevirtual 86	com/alibaba/fastjson/parser/JSONScanner:getCalendar	()Ljava/util/Calendar;
    //   165: invokevirtual 92	java/util/Calendar:getTime	()Ljava/util/Date;
    //   168: astore 4
    //   170: aload 8
    //   172: invokevirtual 95	com/alibaba/fastjson/parser/JSONScanner:close	()V
    //   175: aload_2
    //   176: astore 10
    //   178: goto -131 -> 47
    //   181: astore 8
    //   183: aload 4
    //   185: ldc 97
    //   187: invokevirtual 103	java/lang/String:equals	(Ljava/lang/Object;)Z
    //   190: ifeq +21 -> 211
    //   193: ldc 105
    //   195: astore 4
    //   197: new 58	java/text/SimpleDateFormat
    //   200: dup
    //   201: ldc 105
    //   203: invokespecial 61	java/text/SimpleDateFormat:<init>	(Ljava/lang/String;)V
    //   206: astore 8
    //   208: goto -110 -> 98
    //   211: aload 4
    //   213: ldc 107
    //   215: invokevirtual 103	java/lang/String:equals	(Ljava/lang/Object;)Z
    //   218: ifeq +438 -> 656
    //   221: ldc 109
    //   223: astore 4
    //   225: new 58	java/text/SimpleDateFormat
    //   228: dup
    //   229: ldc 109
    //   231: invokespecial 61	java/text/SimpleDateFormat:<init>	(Ljava/lang/String;)V
    //   234: astore 8
    //   236: goto -138 -> 98
    //   239: astore 8
    //   241: aload 10
    //   243: astore 8
    //   245: aload 4
    //   247: ldc 105
    //   249: invokevirtual 103	java/lang/String:equals	(Ljava/lang/Object;)Z
    //   252: ifeq -145 -> 107
    //   255: aload 10
    //   257: astore 8
    //   259: aload 9
    //   261: invokevirtual 112	java/lang/String:length	()I
    //   264: bipush 19
    //   266: if_icmpne -159 -> 107
    //   269: new 58	java/text/SimpleDateFormat
    //   272: dup
    //   273: ldc 109
    //   275: invokespecial 61	java/text/SimpleDateFormat:<init>	(Ljava/lang/String;)V
    //   278: aload 9
    //   280: invokevirtual 65	java/text/SimpleDateFormat:parse	(Ljava/lang/String;)Ljava/util/Date;
    //   283: astore 8
    //   285: goto -178 -> 107
    //   288: aload 11
    //   290: invokeinterface 36 1 0
    //   295: bipush 8
    //   297: if_icmpne +20 -> 317
    //   300: aload 11
    //   302: invokeinterface 114 1 0
    //   307: aload 8
    //   309: astore 4
    //   311: aload_2
    //   312: astore 10
    //   314: goto -267 -> 47
    //   317: aload 11
    //   319: invokeinterface 36 1 0
    //   324: bipush 12
    //   326: if_icmpne +196 -> 522
    //   329: aload 11
    //   331: invokeinterface 114 1 0
    //   336: aload 11
    //   338: invokeinterface 36 1 0
    //   343: iconst_4
    //   344: if_icmpne +135 -> 479
    //   347: aload 11
    //   349: invokeinterface 56 1 0
    //   354: astore 4
    //   356: aload_2
    //   357: astore 8
    //   359: getstatic 120	com/alibaba/fastjson/a:c	Ljava/lang/String;
    //   362: aload 4
    //   364: invokevirtual 103	java/lang/String:equals	(Ljava/lang/Object;)Z
    //   367: ifeq +57 -> 424
    //   370: aload 11
    //   372: invokeinterface 114 1 0
    //   377: aload_1
    //   378: bipush 17
    //   380: invokevirtual 123	com/alibaba/fastjson/parser/DefaultJSONParser:accept	(I)V
    //   383: aload 11
    //   385: invokeinterface 56 1 0
    //   390: aload_1
    //   391: invokevirtual 127	com/alibaba/fastjson/parser/DefaultJSONParser:getConfig	()Lcom/alibaba/fastjson/parser/ParserConfig;
    //   394: invokevirtual 133	com/alibaba/fastjson/parser/ParserConfig:getDefaultClassLoader	()Ljava/lang/ClassLoader;
    //   397: invokestatic 139	com/alibaba/fastjson/util/TypeUtils:loadClass	(Ljava/lang/String;Ljava/lang/ClassLoader;)Ljava/lang/Class;
    //   400: astore 4
    //   402: aload 4
    //   404: ifnull +6 -> 410
    //   407: aload 4
    //   409: astore_2
    //   410: aload_1
    //   411: iconst_4
    //   412: invokevirtual 123	com/alibaba/fastjson/parser/DefaultJSONParser:accept	(I)V
    //   415: aload_1
    //   416: bipush 16
    //   418: invokevirtual 123	com/alibaba/fastjson/parser/DefaultJSONParser:accept	(I)V
    //   421: aload_2
    //   422: astore 8
    //   424: aload 11
    //   426: iconst_2
    //   427: invokeinterface 142 2 0
    //   432: aload 11
    //   434: invokeinterface 36 1 0
    //   439: iconst_2
    //   440: if_icmpne +49 -> 489
    //   443: aload 11
    //   445: invokeinterface 40 1 0
    //   450: lstore 6
    //   452: aload 11
    //   454: invokeinterface 114 1 0
    //   459: lload 6
    //   461: invokestatic 46	java/lang/Long:valueOf	(J)Ljava/lang/Long;
    //   464: astore 4
    //   466: aload_1
    //   467: bipush 13
    //   469: invokevirtual 123	com/alibaba/fastjson/parser/DefaultJSONParser:accept	(I)V
    //   472: aload 8
    //   474: astore 10
    //   476: goto -429 -> 47
    //   479: new 144	com/alibaba/fastjson/d
    //   482: dup
    //   483: ldc -110
    //   485: invokespecial 147	com/alibaba/fastjson/d:<init>	(Ljava/lang/String;)V
    //   488: athrow
    //   489: new 144	com/alibaba/fastjson/d
    //   492: dup
    //   493: new 149	java/lang/StringBuilder
    //   496: dup
    //   497: invokespecial 150	java/lang/StringBuilder:<init>	()V
    //   500: ldc -104
    //   502: invokevirtual 156	java/lang/StringBuilder:append	(Ljava/lang/String;)Ljava/lang/StringBuilder;
    //   505: aload 11
    //   507: invokeinterface 159 1 0
    //   512: invokevirtual 156	java/lang/StringBuilder:append	(Ljava/lang/String;)Ljava/lang/StringBuilder;
    //   515: invokevirtual 162	java/lang/StringBuilder:toString	()Ljava/lang/String;
    //   518: invokespecial 147	com/alibaba/fastjson/d:<init>	(Ljava/lang/String;)V
    //   521: athrow
    //   522: aload_1
    //   523: invokevirtual 165	com/alibaba/fastjson/parser/DefaultJSONParser:getResolveStatus	()I
    //   526: iconst_2
    //   527: if_icmpne +91 -> 618
    //   530: aload_1
    //   531: iconst_0
    //   532: invokevirtual 168	com/alibaba/fastjson/parser/DefaultJSONParser:setResolveStatus	(I)V
    //   535: aload_1
    //   536: bipush 16
    //   538: invokevirtual 123	com/alibaba/fastjson/parser/DefaultJSONParser:accept	(I)V
    //   541: aload 11
    //   543: invokeinterface 36 1 0
    //   548: iconst_4
    //   549: if_icmpne +59 -> 608
    //   552: ldc -86
    //   554: aload 11
    //   556: invokeinterface 56 1 0
    //   561: invokevirtual 103	java/lang/String:equals	(Ljava/lang/Object;)Z
    //   564: ifne +13 -> 577
    //   567: new 144	com/alibaba/fastjson/d
    //   570: dup
    //   571: ldc -110
    //   573: invokespecial 147	com/alibaba/fastjson/d:<init>	(Ljava/lang/String;)V
    //   576: athrow
    //   577: aload 11
    //   579: invokeinterface 114 1 0
    //   584: aload_1
    //   585: bipush 17
    //   587: invokevirtual 123	com/alibaba/fastjson/parser/DefaultJSONParser:accept	(I)V
    //   590: aload_1
    //   591: invokevirtual 173	com/alibaba/fastjson/parser/DefaultJSONParser:parse	()Ljava/lang/Object;
    //   594: astore 4
    //   596: aload_1
    //   597: bipush 13
    //   599: invokevirtual 123	com/alibaba/fastjson/parser/DefaultJSONParser:accept	(I)V
    //   602: aload_2
    //   603: astore 10
    //   605: goto -558 -> 47
    //   608: new 144	com/alibaba/fastjson/d
    //   611: dup
    //   612: ldc -110
    //   614: invokespecial 147	com/alibaba/fastjson/d:<init>	(Ljava/lang/String;)V
    //   617: athrow
    //   618: aload_1
    //   619: invokevirtual 173	com/alibaba/fastjson/parser/DefaultJSONParser:parse	()Ljava/lang/Object;
    //   622: astore 4
    //   624: aload_2
    //   625: astore 10
    //   627: goto -580 -> 47
    //   630: astore 4
    //   632: aload 10
    //   634: astore 8
    //   636: goto -529 -> 107
    //   639: aload 9
    //   641: astore 4
    //   643: goto -473 -> 170
    //   646: aload 9
    //   648: astore 4
    //   650: aload_2
    //   651: astore 10
    //   653: goto -606 -> 47
    //   656: aconst_null
    //   657: astore 8
    //   659: goto -561 -> 98
    // Local variable table:
    //   start	length	slot	name	signature
    //   0	662	0	this	AbstractDateDeserializer
    //   0	662	1	paramDefaultJSONParser	DefaultJSONParser
    //   0	662	2	paramType	Type
    //   0	662	3	paramObject	Object
    //   0	662	4	paramString	String
    //   0	662	5	paramInt	int
    //   450	10	6	l	long
    //   4	167	8	localObject1	Object
    //   181	1	8	localIllegalArgumentException	IllegalArgumentException
    //   206	29	8	localSimpleDateFormat	java.text.SimpleDateFormat
    //   239	1	8	localParseException	java.text.ParseException
    //   243	415	8	localObject2	Object
    //   76	571	9	str	String
    //   1	651	10	localObject3	Object
    //   10	568	11	localJSONLexer	com.alibaba.fastjson.parser.JSONLexer
    // Exception table:
    //   from	to	target	type
    //   87	98	181	java/lang/IllegalArgumentException
    //   98	107	239	java/text/ParseException
    //   269	285	630	java/text/ParseException
  }
}


/* Location:              /Users/gaoht/Downloads/zirom/classes-dex2jar.jar!/com/alibaba/fastjson/parser/deserializer/AbstractDateDeserializer.class
 * Java compiler version: 6 (50.0)
 * JD-Core Version:       0.7.1
 */