package com.baidu.location.d;

import com.maa.android.agent.instrumentation.Instrumented;

@Instrumented
class g
  extends Thread
{
  g(e parame, boolean paramBoolean) {}
  
  /* Error */
  public void run()
  {
    // Byte code:
    //   0: aload_0
    //   1: getfield 13	com/baidu/location/d/g:b	Lcom/baidu/location/d/e;
    //   4: invokestatic 30	com/baidu/location/d/j:c	()Ljava/lang/String;
    //   7: putfield 36	com/baidu/location/d/e:h	Ljava/lang/String;
    //   10: aload_0
    //   11: getfield 13	com/baidu/location/d/g:b	Lcom/baidu/location/d/e;
    //   14: invokestatic 39	com/baidu/location/d/e:a	(Lcom/baidu/location/d/e;)V
    //   17: aload_0
    //   18: getfield 13	com/baidu/location/d/g:b	Lcom/baidu/location/d/e;
    //   21: invokevirtual 41	com/baidu/location/d/e:a	()V
    //   24: aload_0
    //   25: getfield 13	com/baidu/location/d/g:b	Lcom/baidu/location/d/e;
    //   28: getfield 45	com/baidu/location/d/e:i	I
    //   31: istore_1
    //   32: aconst_null
    //   33: astore_3
    //   34: iload_1
    //   35: ifle +586 -> 621
    //   38: new 47	java/net/URL
    //   41: dup
    //   42: aload_0
    //   43: getfield 13	com/baidu/location/d/g:b	Lcom/baidu/location/d/e;
    //   46: getfield 36	com/baidu/location/d/e:h	Ljava/lang/String;
    //   49: invokespecial 50	java/net/URL:<init>	(Ljava/lang/String;)V
    //   52: astore 4
    //   54: new 52	java/lang/StringBuffer
    //   57: dup
    //   58: invokespecial 53	java/lang/StringBuffer:<init>	()V
    //   61: astore 5
    //   63: aload_0
    //   64: getfield 13	com/baidu/location/d/g:b	Lcom/baidu/location/d/e;
    //   67: getfield 57	com/baidu/location/d/e:k	Ljava/util/Map;
    //   70: invokeinterface 63 1 0
    //   75: invokeinterface 69 1 0
    //   80: astore 6
    //   82: aload 6
    //   84: invokeinterface 75 1 0
    //   89: ifeq +103 -> 192
    //   92: aload 6
    //   94: invokeinterface 79 1 0
    //   99: checkcast 81	java/util/Map$Entry
    //   102: astore 7
    //   104: aload 5
    //   106: aload 7
    //   108: invokeinterface 84 1 0
    //   113: checkcast 86	java/lang/String
    //   116: invokevirtual 90	java/lang/StringBuffer:append	(Ljava/lang/String;)Ljava/lang/StringBuffer;
    //   119: pop
    //   120: aload 5
    //   122: ldc 92
    //   124: invokevirtual 90	java/lang/StringBuffer:append	(Ljava/lang/String;)Ljava/lang/StringBuffer;
    //   127: pop
    //   128: aload 5
    //   130: aload 7
    //   132: invokeinterface 95 1 0
    //   137: invokevirtual 98	java/lang/StringBuffer:append	(Ljava/lang/Object;)Ljava/lang/StringBuffer;
    //   140: pop
    //   141: aload 5
    //   143: ldc 100
    //   145: invokevirtual 90	java/lang/StringBuffer:append	(Ljava/lang/String;)Ljava/lang/StringBuffer;
    //   148: pop
    //   149: goto -67 -> 82
    //   152: astore 4
    //   154: aload_3
    //   155: astore 4
    //   157: aload 4
    //   159: astore_3
    //   160: getstatic 104	com/baidu/location/d/a:a	Ljava/lang/String;
    //   163: ldc 106
    //   165: invokestatic 112	android/util/Log:d	(Ljava/lang/String;Ljava/lang/String;)I
    //   168: pop
    //   169: aload 4
    //   171: astore_3
    //   172: aload 4
    //   174: ifnull +11 -> 185
    //   177: aload 4
    //   179: invokevirtual 117	java/net/HttpURLConnection:disconnect	()V
    //   182: aload 4
    //   184: astore_3
    //   185: iload_1
    //   186: iconst_1
    //   187: isub
    //   188: istore_1
    //   189: goto -155 -> 34
    //   192: aload 5
    //   194: invokevirtual 121	java/lang/StringBuffer:length	()I
    //   197: ifle +16 -> 213
    //   200: aload 5
    //   202: aload 5
    //   204: invokevirtual 121	java/lang/StringBuffer:length	()I
    //   207: iconst_1
    //   208: isub
    //   209: invokevirtual 125	java/lang/StringBuffer:deleteCharAt	(I)Ljava/lang/StringBuffer;
    //   212: pop
    //   213: aload 4
    //   215: instanceof 47
    //   218: ifne +296 -> 514
    //   221: aload 4
    //   223: invokevirtual 129	java/net/URL:openConnection	()Ljava/net/URLConnection;
    //   226: astore 4
    //   228: aload 4
    //   230: checkcast 114	java/net/HttpURLConnection
    //   233: astore 4
    //   235: aload 4
    //   237: astore_3
    //   238: aload 4
    //   240: ldc -125
    //   242: invokevirtual 134	java/net/HttpURLConnection:setRequestMethod	(Ljava/lang/String;)V
    //   245: aload 4
    //   247: astore_3
    //   248: aload 4
    //   250: iconst_1
    //   251: invokevirtual 138	java/net/HttpURLConnection:setDoInput	(Z)V
    //   254: aload 4
    //   256: astore_3
    //   257: aload 4
    //   259: iconst_1
    //   260: invokevirtual 141	java/net/HttpURLConnection:setDoOutput	(Z)V
    //   263: aload 4
    //   265: astore_3
    //   266: aload 4
    //   268: iconst_0
    //   269: invokevirtual 144	java/net/HttpURLConnection:setUseCaches	(Z)V
    //   272: aload 4
    //   274: astore_3
    //   275: aload 4
    //   277: getstatic 146	com/baidu/location/d/a:b	I
    //   280: invokevirtual 150	java/net/HttpURLConnection:setConnectTimeout	(I)V
    //   283: aload 4
    //   285: astore_3
    //   286: aload 4
    //   288: getstatic 146	com/baidu/location/d/a:b	I
    //   291: invokevirtual 153	java/net/HttpURLConnection:setReadTimeout	(I)V
    //   294: aload 4
    //   296: astore_3
    //   297: aload 4
    //   299: ldc -101
    //   301: ldc -99
    //   303: invokevirtual 161	java/net/HttpURLConnection:setRequestProperty	(Ljava/lang/String;Ljava/lang/String;)V
    //   306: aload 4
    //   308: astore_3
    //   309: aload 4
    //   311: ldc -93
    //   313: ldc -91
    //   315: invokevirtual 161	java/net/HttpURLConnection:setRequestProperty	(Ljava/lang/String;Ljava/lang/String;)V
    //   318: aload 4
    //   320: astore_3
    //   321: aload 4
    //   323: ldc -89
    //   325: ldc -87
    //   327: invokevirtual 161	java/net/HttpURLConnection:setRequestProperty	(Ljava/lang/String;Ljava/lang/String;)V
    //   330: aload 4
    //   332: astore_3
    //   333: aload 4
    //   335: ldc -85
    //   337: ldc -83
    //   339: invokevirtual 161	java/net/HttpURLConnection:setRequestProperty	(Ljava/lang/String;Ljava/lang/String;)V
    //   342: aload 4
    //   344: astore_3
    //   345: aload 4
    //   347: invokevirtual 177	java/net/HttpURLConnection:getOutputStream	()Ljava/io/OutputStream;
    //   350: astore 6
    //   352: aload 4
    //   354: astore_3
    //   355: aload 6
    //   357: aload 5
    //   359: invokevirtual 180	java/lang/StringBuffer:toString	()Ljava/lang/String;
    //   362: invokevirtual 184	java/lang/String:getBytes	()[B
    //   365: invokevirtual 190	java/io/OutputStream:write	([B)V
    //   368: aload 4
    //   370: astore_3
    //   371: aload 6
    //   373: invokevirtual 193	java/io/OutputStream:flush	()V
    //   376: aload 4
    //   378: astore_3
    //   379: aload 6
    //   381: invokevirtual 196	java/io/OutputStream:close	()V
    //   384: aload 4
    //   386: astore_3
    //   387: aload 4
    //   389: invokevirtual 199	java/net/HttpURLConnection:getResponseCode	()I
    //   392: sipush 200
    //   395: if_icmpne +255 -> 650
    //   398: aload 4
    //   400: astore_3
    //   401: aload 4
    //   403: invokevirtual 203	java/net/HttpURLConnection:getInputStream	()Ljava/io/InputStream;
    //   406: astore 5
    //   408: aload 4
    //   410: astore_3
    //   411: aload 4
    //   413: invokevirtual 206	java/net/HttpURLConnection:getContentEncoding	()Ljava/lang/String;
    //   416: astore 6
    //   418: aload 6
    //   420: ifnull +321 -> 741
    //   423: aload 4
    //   425: astore_3
    //   426: aload 6
    //   428: ldc -87
    //   430: invokevirtual 210	java/lang/String:contains	(Ljava/lang/CharSequence;)Z
    //   433: ifeq +308 -> 741
    //   436: aload 4
    //   438: astore_3
    //   439: new 212	java/util/zip/GZIPInputStream
    //   442: dup
    //   443: new 214	java/io/BufferedInputStream
    //   446: dup
    //   447: aload 5
    //   449: invokespecial 217	java/io/BufferedInputStream:<init>	(Ljava/io/InputStream;)V
    //   452: invokespecial 218	java/util/zip/GZIPInputStream:<init>	(Ljava/io/InputStream;)V
    //   455: astore 5
    //   457: aload 4
    //   459: astore_3
    //   460: new 220	java/io/ByteArrayOutputStream
    //   463: dup
    //   464: invokespecial 221	java/io/ByteArrayOutputStream:<init>	()V
    //   467: astore 6
    //   469: aload 4
    //   471: astore_3
    //   472: sipush 1024
    //   475: newarray <illegal type>
    //   477: astore 7
    //   479: aload 4
    //   481: astore_3
    //   482: aload 5
    //   484: aload 7
    //   486: invokevirtual 227	java/io/InputStream:read	([B)I
    //   489: istore_2
    //   490: iload_2
    //   491: iconst_m1
    //   492: if_icmpeq +35 -> 527
    //   495: aload 4
    //   497: astore_3
    //   498: aload 6
    //   500: aload 7
    //   502: iconst_0
    //   503: iload_2
    //   504: invokevirtual 230	java/io/ByteArrayOutputStream:write	([BII)V
    //   507: goto -28 -> 479
    //   510: astore_3
    //   511: goto -354 -> 157
    //   514: aload 4
    //   516: checkcast 47	java/net/URL
    //   519: invokestatic 235	com/mato/sdk/instrumentation/HttpInstrumentation:openConnection	(Ljava/net/URL;)Ljava/net/URLConnection;
    //   522: astore 4
    //   524: goto -296 -> 228
    //   527: aload 4
    //   529: astore_3
    //   530: aload 5
    //   532: invokevirtual 236	java/io/InputStream:close	()V
    //   535: aload 4
    //   537: astore_3
    //   538: aload 6
    //   540: invokevirtual 237	java/io/ByteArrayOutputStream:close	()V
    //   543: aload 4
    //   545: astore_3
    //   546: aload_0
    //   547: getfield 13	com/baidu/location/d/g:b	Lcom/baidu/location/d/e;
    //   550: new 86	java/lang/String
    //   553: dup
    //   554: aload 6
    //   556: invokevirtual 240	java/io/ByteArrayOutputStream:toByteArray	()[B
    //   559: ldc -14
    //   561: invokespecial 245	java/lang/String:<init>	([BLjava/lang/String;)V
    //   564: putfield 248	com/baidu/location/d/e:j	Ljava/lang/String;
    //   567: aload 4
    //   569: astore_3
    //   570: aload_0
    //   571: getfield 15	com/baidu/location/d/g:a	Z
    //   574: ifeq +18 -> 592
    //   577: aload 4
    //   579: astore_3
    //   580: aload_0
    //   581: getfield 13	com/baidu/location/d/g:b	Lcom/baidu/location/d/e;
    //   584: aload 6
    //   586: invokevirtual 240	java/io/ByteArrayOutputStream:toByteArray	()[B
    //   589: putfield 252	com/baidu/location/d/e:m	[B
    //   592: aload 4
    //   594: astore_3
    //   595: aload_0
    //   596: getfield 13	com/baidu/location/d/g:b	Lcom/baidu/location/d/e;
    //   599: iconst_1
    //   600: invokevirtual 254	com/baidu/location/d/e:a	(Z)V
    //   603: aload 4
    //   605: astore_3
    //   606: aload 4
    //   608: invokevirtual 117	java/net/HttpURLConnection:disconnect	()V
    //   611: aload 4
    //   613: ifnull +8 -> 621
    //   616: aload 4
    //   618: invokevirtual 117	java/net/HttpURLConnection:disconnect	()V
    //   621: iload_1
    //   622: ifgt +101 -> 723
    //   625: getstatic 257	com/baidu/location/d/e:o	I
    //   628: iconst_1
    //   629: iadd
    //   630: putstatic 257	com/baidu/location/d/e:o	I
    //   633: aload_0
    //   634: getfield 13	com/baidu/location/d/g:b	Lcom/baidu/location/d/e;
    //   637: aconst_null
    //   638: putfield 248	com/baidu/location/d/e:j	Ljava/lang/String;
    //   641: aload_0
    //   642: getfield 13	com/baidu/location/d/g:b	Lcom/baidu/location/d/e;
    //   645: iconst_0
    //   646: invokevirtual 254	com/baidu/location/d/e:a	(Z)V
    //   649: return
    //   650: aload 4
    //   652: astore_3
    //   653: aload 4
    //   655: invokevirtual 117	java/net/HttpURLConnection:disconnect	()V
    //   658: aload 4
    //   660: astore_3
    //   661: aload 4
    //   663: ifnull -478 -> 185
    //   666: aload 4
    //   668: invokevirtual 117	java/net/HttpURLConnection:disconnect	()V
    //   671: aload 4
    //   673: astore_3
    //   674: goto -489 -> 185
    //   677: astore_3
    //   678: aload 4
    //   680: astore_3
    //   681: getstatic 104	com/baidu/location/d/a:a	Ljava/lang/String;
    //   684: ldc_w 259
    //   687: invokestatic 112	android/util/Log:d	(Ljava/lang/String;Ljava/lang/String;)I
    //   690: pop
    //   691: aload 4
    //   693: astore_3
    //   694: aload 4
    //   696: ifnull -511 -> 185
    //   699: aload 4
    //   701: invokevirtual 117	java/net/HttpURLConnection:disconnect	()V
    //   704: aload 4
    //   706: astore_3
    //   707: goto -522 -> 185
    //   710: astore 4
    //   712: aload_3
    //   713: ifnull +7 -> 720
    //   716: aload_3
    //   717: invokevirtual 117	java/net/HttpURLConnection:disconnect	()V
    //   720: aload 4
    //   722: athrow
    //   723: iconst_0
    //   724: putstatic 257	com/baidu/location/d/e:o	I
    //   727: return
    //   728: astore 4
    //   730: goto -18 -> 712
    //   733: astore 4
    //   735: aload_3
    //   736: astore 4
    //   738: goto -60 -> 678
    //   741: goto -284 -> 457
    // Local variable table:
    //   start	length	slot	name	signature
    //   0	744	0	this	g
    //   31	591	1	i	int
    //   489	15	2	j	int
    //   33	465	3	localObject1	Object
    //   510	1	3	localException1	Exception
    //   529	145	3	localObject2	Object
    //   677	1	3	localError1	Error
    //   680	56	3	localObject3	Object
    //   52	1	4	localURL	java.net.URL
    //   152	1	4	localException2	Exception
    //   155	550	4	localObject4	Object
    //   710	11	4	localObject5	Object
    //   728	1	4	localObject6	Object
    //   733	1	4	localError2	Error
    //   736	1	4	localObject7	Object
    //   61	470	5	localObject8	Object
    //   80	505	6	localObject9	Object
    //   102	399	7	localObject10	Object
    // Exception table:
    //   from	to	target	type
    //   38	82	152	java/lang/Exception
    //   82	149	152	java/lang/Exception
    //   192	213	152	java/lang/Exception
    //   213	228	152	java/lang/Exception
    //   228	235	152	java/lang/Exception
    //   514	524	152	java/lang/Exception
    //   238	245	510	java/lang/Exception
    //   248	254	510	java/lang/Exception
    //   257	263	510	java/lang/Exception
    //   266	272	510	java/lang/Exception
    //   275	283	510	java/lang/Exception
    //   286	294	510	java/lang/Exception
    //   297	306	510	java/lang/Exception
    //   309	318	510	java/lang/Exception
    //   321	330	510	java/lang/Exception
    //   333	342	510	java/lang/Exception
    //   345	352	510	java/lang/Exception
    //   355	368	510	java/lang/Exception
    //   371	376	510	java/lang/Exception
    //   379	384	510	java/lang/Exception
    //   387	398	510	java/lang/Exception
    //   401	408	510	java/lang/Exception
    //   411	418	510	java/lang/Exception
    //   426	436	510	java/lang/Exception
    //   439	457	510	java/lang/Exception
    //   460	469	510	java/lang/Exception
    //   472	479	510	java/lang/Exception
    //   482	490	510	java/lang/Exception
    //   498	507	510	java/lang/Exception
    //   530	535	510	java/lang/Exception
    //   538	543	510	java/lang/Exception
    //   546	567	510	java/lang/Exception
    //   570	577	510	java/lang/Exception
    //   580	592	510	java/lang/Exception
    //   595	603	510	java/lang/Exception
    //   606	611	510	java/lang/Exception
    //   653	658	510	java/lang/Exception
    //   238	245	677	java/lang/Error
    //   248	254	677	java/lang/Error
    //   257	263	677	java/lang/Error
    //   266	272	677	java/lang/Error
    //   275	283	677	java/lang/Error
    //   286	294	677	java/lang/Error
    //   297	306	677	java/lang/Error
    //   309	318	677	java/lang/Error
    //   321	330	677	java/lang/Error
    //   333	342	677	java/lang/Error
    //   345	352	677	java/lang/Error
    //   355	368	677	java/lang/Error
    //   371	376	677	java/lang/Error
    //   379	384	677	java/lang/Error
    //   387	398	677	java/lang/Error
    //   401	408	677	java/lang/Error
    //   411	418	677	java/lang/Error
    //   426	436	677	java/lang/Error
    //   439	457	677	java/lang/Error
    //   460	469	677	java/lang/Error
    //   472	479	677	java/lang/Error
    //   482	490	677	java/lang/Error
    //   498	507	677	java/lang/Error
    //   530	535	677	java/lang/Error
    //   538	543	677	java/lang/Error
    //   546	567	677	java/lang/Error
    //   570	577	677	java/lang/Error
    //   580	592	677	java/lang/Error
    //   595	603	677	java/lang/Error
    //   606	611	677	java/lang/Error
    //   653	658	677	java/lang/Error
    //   160	169	710	finally
    //   238	245	710	finally
    //   248	254	710	finally
    //   257	263	710	finally
    //   266	272	710	finally
    //   275	283	710	finally
    //   286	294	710	finally
    //   297	306	710	finally
    //   309	318	710	finally
    //   321	330	710	finally
    //   333	342	710	finally
    //   345	352	710	finally
    //   355	368	710	finally
    //   371	376	710	finally
    //   379	384	710	finally
    //   387	398	710	finally
    //   401	408	710	finally
    //   411	418	710	finally
    //   426	436	710	finally
    //   439	457	710	finally
    //   460	469	710	finally
    //   472	479	710	finally
    //   482	490	710	finally
    //   498	507	710	finally
    //   530	535	710	finally
    //   538	543	710	finally
    //   546	567	710	finally
    //   570	577	710	finally
    //   580	592	710	finally
    //   595	603	710	finally
    //   606	611	710	finally
    //   653	658	710	finally
    //   681	691	710	finally
    //   38	82	728	finally
    //   82	149	728	finally
    //   192	213	728	finally
    //   213	228	728	finally
    //   228	235	728	finally
    //   514	524	728	finally
    //   38	82	733	java/lang/Error
    //   82	149	733	java/lang/Error
    //   192	213	733	java/lang/Error
    //   213	228	733	java/lang/Error
    //   228	235	733	java/lang/Error
    //   514	524	733	java/lang/Error
  }
}


/* Location:              /Users/gaoht/Downloads/zirom/classes-dex2jar.jar!/com/baidu/location/d/g.class
 * Java compiler version: 6 (50.0)
 * JD-Core Version:       0.7.1
 */