package com.alipay.b.d;

public final class d
{
  /* Error */
  public static java.util.Map<String, String> a()
  {
    // Byte code:
    //   0: ldc 2
    //   2: monitorenter
    //   3: new 10	java/util/HashMap
    //   6: dup
    //   7: invokespecial 14	java/util/HashMap:<init>	()V
    //   10: astore_0
    //   11: new 16	com/alipay/b/c/b
    //   14: dup
    //   15: invokespecial 17	com/alipay/b/c/b:<init>	()V
    //   18: pop
    //   19: aload_0
    //   20: ldc 19
    //   22: ldc 21
    //   24: invokeinterface 27 3 0
    //   29: pop
    //   30: ldc 2
    //   32: monitorexit
    //   33: aload_0
    //   34: areturn
    //   35: astore_0
    //   36: ldc 2
    //   38: monitorexit
    //   39: aload_0
    //   40: athrow
    //   41: astore_1
    //   42: goto -12 -> 30
    // Local variable table:
    //   start	length	slot	name	signature
    //   10	24	0	localHashMap	java.util.HashMap
    //   35	5	0	localObject	Object
    //   41	1	1	localThrowable	Throwable
    // Exception table:
    //   from	to	target	type
    //   3	11	35	finally
    //   11	30	35	finally
    //   11	30	41	java/lang/Throwable
  }
  
  /* Error */
  public static java.util.Map<String, String> a(android.content.Context paramContext)
  {
    // Byte code:
    //   0: ldc 2
    //   2: monitorenter
    //   3: invokestatic 36	com/alipay/c/a/a/b/d:a	()Lcom/alipay/c/a/a/b/d;
    //   6: pop
    //   7: invokestatic 41	com/alipay/c/a/a/b/b:a	()Lcom/alipay/c/a/a/b/b;
    //   10: pop
    //   11: new 10	java/util/HashMap
    //   14: dup
    //   15: invokespecial 14	java/util/HashMap:<init>	()V
    //   18: astore_2
    //   19: aload_2
    //   20: ldc 43
    //   22: invokestatic 47	com/alipay/c/a/a/b/d:b	()Ljava/lang/String;
    //   25: invokeinterface 27 3 0
    //   30: pop
    //   31: new 49	java/lang/StringBuilder
    //   34: dup
    //   35: invokespecial 50	java/lang/StringBuilder:<init>	()V
    //   38: astore_3
    //   39: invokestatic 54	com/alipay/c/a/a/b/d:c	()Z
    //   42: ifeq +219 -> 261
    //   45: ldc 56
    //   47: astore_1
    //   48: aload_2
    //   49: ldc 58
    //   51: aload_3
    //   52: aload_1
    //   53: invokevirtual 62	java/lang/StringBuilder:append	(Ljava/lang/String;)Ljava/lang/StringBuilder;
    //   56: invokevirtual 65	java/lang/StringBuilder:toString	()Ljava/lang/String;
    //   59: invokeinterface 27 3 0
    //   64: pop
    //   65: new 49	java/lang/StringBuilder
    //   68: dup
    //   69: invokespecial 50	java/lang/StringBuilder:<init>	()V
    //   72: astore_1
    //   73: aload_0
    //   74: invokestatic 68	com/alipay/c/a/a/b/d:a	(Landroid/content/Context;)Z
    //   77: ifeq +190 -> 267
    //   80: ldc 56
    //   82: astore_0
    //   83: aload_2
    //   84: ldc 70
    //   86: aload_1
    //   87: aload_0
    //   88: invokevirtual 62	java/lang/StringBuilder:append	(Ljava/lang/String;)Ljava/lang/StringBuilder;
    //   91: invokevirtual 65	java/lang/StringBuilder:toString	()Ljava/lang/String;
    //   94: invokeinterface 27 3 0
    //   99: pop
    //   100: aload_2
    //   101: ldc 72
    //   103: invokestatic 75	com/alipay/c/a/a/b/d:d	()Ljava/lang/String;
    //   106: invokeinterface 27 3 0
    //   111: pop
    //   112: aload_2
    //   113: ldc 77
    //   115: invokestatic 80	com/alipay/c/a/a/b/d:e	()Ljava/lang/String;
    //   118: invokeinterface 27 3 0
    //   123: pop
    //   124: aload_2
    //   125: ldc 82
    //   127: invokestatic 85	com/alipay/c/a/a/b/d:f	()Ljava/lang/String;
    //   130: invokeinterface 27 3 0
    //   135: pop
    //   136: aload_2
    //   137: ldc 87
    //   139: invokestatic 90	com/alipay/c/a/a/b/d:g	()Ljava/lang/String;
    //   142: invokeinterface 27 3 0
    //   147: pop
    //   148: aload_2
    //   149: ldc 92
    //   151: invokestatic 95	com/alipay/c/a/a/b/d:h	()Ljava/lang/String;
    //   154: invokeinterface 27 3 0
    //   159: pop
    //   160: aload_2
    //   161: ldc 97
    //   163: invokestatic 100	com/alipay/c/a/a/b/d:i	()Ljava/lang/String;
    //   166: invokeinterface 27 3 0
    //   171: pop
    //   172: aload_2
    //   173: ldc 102
    //   175: invokestatic 105	com/alipay/c/a/a/b/d:j	()Ljava/lang/String;
    //   178: invokeinterface 27 3 0
    //   183: pop
    //   184: aload_2
    //   185: ldc 107
    //   187: invokestatic 110	com/alipay/c/a/a/b/d:k	()Ljava/lang/String;
    //   190: invokeinterface 27 3 0
    //   195: pop
    //   196: aload_2
    //   197: ldc 112
    //   199: invokestatic 115	com/alipay/c/a/a/b/d:l	()Ljava/lang/String;
    //   202: invokeinterface 27 3 0
    //   207: pop
    //   208: aload_2
    //   209: ldc 117
    //   211: invokestatic 120	com/alipay/c/a/a/b/d:m	()Ljava/lang/String;
    //   214: invokeinterface 27 3 0
    //   219: pop
    //   220: aload_2
    //   221: ldc 122
    //   223: invokestatic 125	com/alipay/c/a/a/b/d:n	()Ljava/lang/String;
    //   226: invokeinterface 27 3 0
    //   231: pop
    //   232: aload_2
    //   233: ldc 127
    //   235: invokestatic 130	com/alipay/c/a/a/b/d:o	()Ljava/lang/String;
    //   238: invokeinterface 27 3 0
    //   243: pop
    //   244: aload_2
    //   245: ldc -124
    //   247: invokestatic 133	com/alipay/c/a/a/b/b:g	()Ljava/lang/String;
    //   250: invokeinterface 27 3 0
    //   255: pop
    //   256: ldc 2
    //   258: monitorexit
    //   259: aload_2
    //   260: areturn
    //   261: ldc -121
    //   263: astore_1
    //   264: goto -216 -> 48
    //   267: ldc -121
    //   269: astore_0
    //   270: goto -187 -> 83
    //   273: astore_0
    //   274: ldc 2
    //   276: monitorexit
    //   277: aload_0
    //   278: athrow
    // Local variable table:
    //   start	length	slot	name	signature
    //   0	279	0	paramContext	android.content.Context
    //   47	217	1	localObject	Object
    //   18	242	2	localHashMap	java.util.HashMap
    //   38	14	3	localStringBuilder	StringBuilder
    // Exception table:
    //   from	to	target	type
    //   3	45	273	finally
    //   48	80	273	finally
    //   83	256	273	finally
  }
}


/* Location:              /Users/gaoht/Downloads/zirom/classes-dex2jar.jar!/com/alipay/b/d/d.class
 * Java compiler version: 6 (50.0)
 * JD-Core Version:       0.7.1
 */