package cn.testin.analysis;

import android.content.Context;
import android.content.SharedPreferences;
import android.content.SharedPreferences.Editor;
import android.os.Handler;
import android.os.Looper;
import android.text.TextUtils;
import android.util.Pair;
import java.util.ArrayList;
import java.util.HashMap;
import java.util.Iterator;
import java.util.List;
import java.util.Map;
import java.util.Map.Entry;
import java.util.Set;
import org.json.JSONArray;
import org.json.JSONException;
import org.json.JSONObject;

public class u
  extends r
{
  private static HashMap<String, Object> j = new HashMap();
  private static boolean k;
  private final String b = "CONTROL";
  private final String c = "expt";
  private final List<y> d = new ArrayList();
  private final List<b> e = new ArrayList();
  private final List<Pair<String, String>> f = new ArrayList();
  private volatile boolean g = false;
  private final Object h = new Object();
  private Map<String, i> i = new HashMap();
  private Handler l;
  private Handler m;
  
  protected u(Context paramContext, Handler paramHandler)
  {
    super(paramContext);
    this.m = paramHandler;
    a();
    d();
  }
  
  public static void a(Context paramContext, HashMap<String, Object> paramHashMap, boolean paramBoolean)
  {
    for (;;)
    {
      Object localObject;
      String str;
      synchronized (j)
      {
        j.clear();
        if ((paramHashMap == null) || (paramHashMap.isEmpty())) {
          break;
        }
        paramHashMap = paramHashMap.entrySet().iterator();
        if (!paramHashMap.hasNext()) {
          break;
        }
        localObject = (Map.Entry)paramHashMap.next();
        str = (String)((Map.Entry)localObject).getKey();
        localObject = ((Map.Entry)localObject).getValue();
        if (str.getBytes().length > 40) {
          ar.e("自定义标签key长度超过最大限制40字节");
        }
      }
      if ((localObject != null) && ((localObject instanceof String)) && (((String)localObject).getBytes().length > 40))
      {
        ar.e("自定义标签value长度超过最大限制40字节");
      }
      else
      {
        if (j.size() < 20) {
          j.put(str, localObject);
        }
        if (j.size() >= 20) {
          ar.e("自定义标签数量超过最大限制20条");
        }
      }
    }
    for (;;)
    {
      return;
      do
      {
        au.a(paramContext, "labels", aq.a(j));
        return;
        if (!paramBoolean) {
          break;
        }
      } while (paramContext != null);
    }
  }
  
  private void a(OnExpUpdateListener paramOnExpUpdateListener, boolean paramBoolean)
  {
    if (paramOnExpUpdateListener != null)
    {
      if (this.l == null) {
        this.l = new Handler(Looper.getMainLooper());
      }
      this.l.post(new x(this, paramOnExpUpdateListener, paramBoolean));
    }
  }
  
  private void a(k arg1)
  {
    HashMap localHashMap = new HashMap();
    ArrayList localArrayList = new ArrayList();
    if ((??? == null) || (???.c == null) || (???.c.h == null) || (???.c.h.size() < 1)) {
      ar.d("There is no data cash!!!");
    }
    synchronized (this.i)
    {
      this.i.clear();
      this.i.putAll(localHashMap);
      this.f.clear();
      this.f.addAll(localArrayList);
      au.a(au.b(this.a), "variables", aq.a(localHashMap));
      au.a(au.b(this.a), "pvs_triggerable", aq.a(localArrayList));
      return;
      ??? = ???.c.h.iterator();
      Object localObject2;
      Pair localPair;
      do
      {
        do
        {
          if (!???.hasNext()) {
            break;
          }
          localObject2 = (m)???.next();
          localPair = new Pair(((m)localObject2).c, ((m)localObject2).g);
          if (((m)localObject2).e == 1) {
            localArrayList.add(localPair);
          }
        } while ((((m)localObject2).h == null) || (((m)localObject2).h.size() == 0));
        localObject2 = ((m)localObject2).h.entrySet().iterator();
      } while (!((Iterator)localObject2).hasNext());
      Map.Entry localEntry = (Map.Entry)((Iterator)localObject2).next();
      localHashMap.put((String)localEntry.getKey(), new i(localEntry.getValue(), localPair));
    }
  }
  
  private void b(k paramk)
  {
    JSONArray localJSONArray1 = new JSONArray();
    Object localObject1;
    int n;
    if ((paramk != null) && (paramk.c != null)) {
      if ((paramk.c.h != null) && (paramk.c.h.size() != 0))
      {
        localObject1 = paramk.c.h;
        n = 0;
      }
    }
    for (;;)
    {
      Object localObject3;
      Object localObject2;
      if (n < ((List)localObject1).size())
      {
        localObject3 = (m)((List)localObject1).get(n);
        if (localObject3 != null) {
          try
          {
            localObject2 = new JSONObject();
            ((JSONObject)localObject2).put("layerId", ((m)localObject3).a);
            ((JSONObject)localObject2).put("layerName", ((m)localObject3).b);
            if (TextUtils.isEmpty(((m)localObject3).g))
            {
              str1 = "CONTROL";
              ((JSONObject)localObject2).put("expId", str1);
              if (!TextUtils.isEmpty(((m)localObject3).j)) {
                break label236;
              }
              str1 = "CONTROL";
              label158:
              ((JSONObject)localObject2).put("expName", str1);
              if (!TextUtils.isEmpty(((m)localObject3).c)) {
                break label245;
              }
              str1 = "CONTROL";
              label182:
              ((JSONObject)localObject2).put("expVersionId", str1);
              if (!TextUtils.isEmpty(((m)localObject3).d)) {
                break label254;
              }
            }
            label236:
            label245:
            label254:
            for (String str1 = "CONTROL";; str1 = ((m)localObject3).d)
            {
              ((JSONObject)localObject2).put("expVersionName", str1);
              localJSONArray1.put(localObject2);
              break label531;
              str1 = ((m)localObject3).g;
              break;
              str1 = ((m)localObject3).j;
              break label158;
              str1 = ((m)localObject3).c;
              break label182;
            }
            if (TextUtils.isEmpty(paramk.c.i)) {
              break label512;
            }
          }
          catch (JSONException localJSONException)
          {
            ar.b(localJSONException);
          }
        }
      }
      else
      {
        try
        {
          JSONArray localJSONArray2 = new JSONArray(paramk.c.i);
          n = 0;
          while (n < localJSONArray2.length())
          {
            paramk = localJSONArray2.optJSONObject(n);
            if (paramk != null)
            {
              JSONObject localJSONObject = new JSONObject();
              localObject3 = paramk.optString("experiment_id");
              localObject2 = paramk.optString("expName");
              localObject1 = paramk.optString("id");
              String str2 = paramk.optString("expVersionName");
              localJSONObject.put("layerId", paramk.optString("layerId"));
              localJSONObject.put("layerName", paramk.optString("layerName"));
              paramk = (k)localObject3;
              if (TextUtils.isEmpty((CharSequence)localObject3)) {
                paramk = "CONTROL";
              }
              localJSONObject.put("expId", paramk);
              paramk = (k)localObject2;
              if (TextUtils.isEmpty((CharSequence)localObject2)) {
                paramk = "CONTROL";
              }
              localJSONObject.put("expName", paramk);
              paramk = (k)localObject1;
              if (TextUtils.isEmpty((CharSequence)localObject1)) {
                paramk = "CONTROL";
              }
              localJSONObject.put("expVersionId", paramk);
              paramk = str2;
              if (TextUtils.isEmpty(str2)) {
                paramk = "CONTROL";
              }
              localJSONObject.put("expVersionName", paramk);
              localJSONArray1.put(localJSONObject);
            }
            n += 1;
          }
          au.a(au.b(this.a), "currentExperimentsInfo", localJSONArray1.toString());
        }
        catch (JSONException paramk)
        {
          ar.b(paramk);
        }
        label512:
        return;
      }
      label531:
      n += 1;
    }
  }
  
  private void b(boolean paramBoolean)
  {
    synchronized (this.d)
    {
      Iterator localIterator = this.d.iterator();
      for (;;)
      {
        if (localIterator.hasNext())
        {
          y localy = (y)localIterator.next();
          y.a(localy);
          try
          {
            a(y.b(localy), paramBoolean);
            y.a(localy, null);
          }
          finally {}
        }
      }
    }
    this.d.clear();
    synchronized (this.h)
    {
      this.g = false;
      return;
    }
  }
  
  private boolean b(String paramString)
  {
    int i1 = 0;
    paramString = (k)aq.a(paramString, k.class);
    if (paramString == null) {
      return false;
    }
    Object localObject = this.a;
    int n;
    if (paramString.a == 1501) {
      n = 0;
    }
    for (;;)
    {
      au.a((Context)localObject, n);
      localObject = au.b(this.a);
      if (paramString.a == 0)
      {
        if (paramString.c != null)
        {
          localObject = ((SharedPreferences)localObject).edit();
          ((SharedPreferences.Editor)localObject).putString("md5", paramString.c.j);
          ((SharedPreferences.Editor)localObject).putInt("downApiInterval", paramString.c.c);
          ((SharedPreferences.Editor)localObject).putInt("downApiTimes", paramString.c.d);
          ((SharedPreferences.Editor)localObject).putInt("upApiInterval", paramString.c.e);
          ((SharedPreferences.Editor)localObject).putInt("upApiTimes", paramString.c.f);
          ((SharedPreferences.Editor)localObject).apply();
        }
        label171:
        if (paramString.a != 1501)
        {
          a(paramString);
          b(paramString);
          localObject = this.e;
          n = i1;
        }
      }
      else
      {
        try
        {
          for (;;)
          {
            if (n < this.e.size())
            {
              ((b)this.e.get(n)).a(paramString);
              n += 1;
              continue;
              n = paramString.a;
              break;
              if (paramString.a == 1501) {
                break label171;
              }
              au.a((SharedPreferences)localObject, "md5", null);
              break label171;
            }
          }
        }
        finally {}
      }
    }
    return true;
  }
  
  /* Error */
  private String c(boolean paramBoolean)
  {
    // Byte code:
    //   0: new 397	cn/testin/analysis/ai
    //   3: dup
    //   4: invokespecial 398	cn/testin/analysis/ai:<init>	()V
    //   7: astore_2
    //   8: aload_2
    //   9: ldc_w 295
    //   12: getstatic 402	cn/testin/analysis/a:h	Ljava/lang/String;
    //   15: invokevirtual 403	cn/testin/analysis/ai:put	(Ljava/lang/Object;Ljava/lang/Object;)Ljava/lang/Object;
    //   18: pop
    //   19: aload_2
    //   20: ldc_w 405
    //   23: iconst_1
    //   24: invokestatic 411	java/lang/Boolean:valueOf	(Z)Ljava/lang/Boolean;
    //   27: invokevirtual 403	cn/testin/analysis/ai:put	(Ljava/lang/Object;Ljava/lang/Object;)Ljava/lang/Object;
    //   30: pop
    //   31: aload_2
    //   32: ldc_w 358
    //   35: aload_0
    //   36: getfield 206	cn/testin/analysis/u:a	Landroid/content/Context;
    //   39: invokestatic 209	cn/testin/analysis/au:b	(Landroid/content/Context;)Landroid/content/SharedPreferences;
    //   42: ldc_w 358
    //   45: aconst_null
    //   46: invokeinterface 415 3 0
    //   51: invokevirtual 403	cn/testin/analysis/ai:put	(Ljava/lang/Object;Ljava/lang/Object;)Ljava/lang/Object;
    //   54: pop
    //   55: aload_2
    //   56: ldc_w 416
    //   59: iload_1
    //   60: invokestatic 411	java/lang/Boolean:valueOf	(Z)Ljava/lang/Boolean;
    //   63: invokevirtual 403	cn/testin/analysis/ai:put	(Ljava/lang/Object;Ljava/lang/Object;)Ljava/lang/Object;
    //   66: pop
    //   67: new 271	org/json/JSONObject
    //   70: dup
    //   71: invokespecial 272	org/json/JSONObject:<init>	()V
    //   74: astore_3
    //   75: aload_3
    //   76: ldc_w 418
    //   79: invokestatic 422	cn/testin/analysis/al:c	()I
    //   82: invokevirtual 425	org/json/JSONObject:put	(Ljava/lang/String;I)Lorg/json/JSONObject;
    //   85: pop
    //   86: aload_3
    //   87: ldc_w 427
    //   90: invokestatic 429	cn/testin/analysis/al:d	()Ljava/lang/String;
    //   93: invokevirtual 279	org/json/JSONObject:put	(Ljava/lang/String;Ljava/lang/Object;)Lorg/json/JSONObject;
    //   96: pop
    //   97: aload_3
    //   98: ldc_w 431
    //   101: getstatic 432	cn/testin/analysis/a:g	Ljava/lang/String;
    //   104: invokevirtual 279	org/json/JSONObject:put	(Ljava/lang/String;Ljava/lang/Object;)Lorg/json/JSONObject;
    //   107: pop
    //   108: aload_3
    //   109: ldc_w 434
    //   112: aload_0
    //   113: getfield 206	cn/testin/analysis/u:a	Landroid/content/Context;
    //   116: invokestatic 437	cn/testin/analysis/al:f	(Landroid/content/Context;)Ljava/lang/String;
    //   119: invokevirtual 279	org/json/JSONObject:put	(Ljava/lang/String;Ljava/lang/Object;)Lorg/json/JSONObject;
    //   122: pop
    //   123: aload_3
    //   124: ldc_w 439
    //   127: aload_0
    //   128: getfield 206	cn/testin/analysis/u:a	Landroid/content/Context;
    //   131: invokestatic 441	cn/testin/analysis/al:g	(Landroid/content/Context;)Ljava/lang/String;
    //   134: invokevirtual 279	org/json/JSONObject:put	(Ljava/lang/String;Ljava/lang/Object;)Lorg/json/JSONObject;
    //   137: pop
    //   138: aload_3
    //   139: ldc_w 443
    //   142: aload_0
    //   143: getfield 206	cn/testin/analysis/u:a	Landroid/content/Context;
    //   146: invokestatic 445	cn/testin/analysis/al:h	(Landroid/content/Context;)Ljava/lang/String;
    //   149: invokevirtual 279	org/json/JSONObject:put	(Ljava/lang/String;Ljava/lang/Object;)Lorg/json/JSONObject;
    //   152: pop
    //   153: aload_3
    //   154: ldc_w 447
    //   157: aload_0
    //   158: getfield 206	cn/testin/analysis/u:a	Landroid/content/Context;
    //   161: invokestatic 449	cn/testin/analysis/al:b	(Landroid/content/Context;)Ljava/lang/String;
    //   164: invokevirtual 279	org/json/JSONObject:put	(Ljava/lang/String;Ljava/lang/Object;)Lorg/json/JSONObject;
    //   167: pop
    //   168: aload_3
    //   169: ldc_w 451
    //   172: new 453	java/lang/StringBuilder
    //   175: dup
    //   176: invokespecial 454	java/lang/StringBuilder:<init>	()V
    //   179: invokestatic 456	cn/testin/analysis/al:a	()Ljava/lang/String;
    //   182: invokevirtual 460	java/lang/StringBuilder:append	(Ljava/lang/String;)Ljava/lang/StringBuilder;
    //   185: ldc_w 462
    //   188: invokevirtual 460	java/lang/StringBuilder:append	(Ljava/lang/String;)Ljava/lang/StringBuilder;
    //   191: invokestatic 464	cn/testin/analysis/al:b	()Ljava/lang/String;
    //   194: invokevirtual 460	java/lang/StringBuilder:append	(Ljava/lang/String;)Ljava/lang/StringBuilder;
    //   197: invokevirtual 465	java/lang/StringBuilder:toString	()Ljava/lang/String;
    //   200: invokevirtual 279	org/json/JSONObject:put	(Ljava/lang/String;Ljava/lang/Object;)Lorg/json/JSONObject;
    //   203: pop
    //   204: aload_3
    //   205: ldc_w 467
    //   208: aload_0
    //   209: getfield 206	cn/testin/analysis/u:a	Landroid/content/Context;
    //   212: invokestatic 470	cn/testin/analysis/al:i	(Landroid/content/Context;)I
    //   215: invokevirtual 425	org/json/JSONObject:put	(Ljava/lang/String;I)Lorg/json/JSONObject;
    //   218: pop
    //   219: aload_3
    //   220: ldc_w 472
    //   223: aload_0
    //   224: getfield 206	cn/testin/analysis/u:a	Landroid/content/Context;
    //   227: invokestatic 474	cn/testin/analysis/al:j	(Landroid/content/Context;)I
    //   230: invokevirtual 425	org/json/JSONObject:put	(Ljava/lang/String;I)Lorg/json/JSONObject;
    //   233: pop
    //   234: aload_3
    //   235: ldc_w 476
    //   238: aload_0
    //   239: getfield 206	cn/testin/analysis/u:a	Landroid/content/Context;
    //   242: invokestatic 480	cn/testin/analysis/at:a	(Landroid/content/Context;)Ljava/lang/String;
    //   245: invokevirtual 279	org/json/JSONObject:put	(Ljava/lang/String;Ljava/lang/Object;)Lorg/json/JSONObject;
    //   248: pop
    //   249: aload_3
    //   250: ldc_w 482
    //   253: aload_0
    //   254: getfield 206	cn/testin/analysis/u:a	Landroid/content/Context;
    //   257: invokestatic 483	cn/testin/analysis/at:b	(Landroid/content/Context;)Ljava/lang/String;
    //   260: invokevirtual 279	org/json/JSONObject:put	(Ljava/lang/String;Ljava/lang/Object;)Lorg/json/JSONObject;
    //   263: pop
    //   264: aload_3
    //   265: ldc_w 485
    //   268: aload_0
    //   269: getfield 206	cn/testin/analysis/u:a	Landroid/content/Context;
    //   272: invokestatic 488	cn/testin/analysis/au:h	(Landroid/content/Context;)Z
    //   275: invokevirtual 491	org/json/JSONObject:put	(Ljava/lang/String;Z)Lorg/json/JSONObject;
    //   278: pop
    //   279: aload_2
    //   280: ldc_w 493
    //   283: aload_3
    //   284: invokevirtual 403	cn/testin/analysis/ai:put	(Ljava/lang/Object;Ljava/lang/Object;)Ljava/lang/Object;
    //   287: pop
    //   288: getstatic 37	cn/testin/analysis/u:j	Ljava/util/HashMap;
    //   291: astore_3
    //   292: aload_3
    //   293: monitorenter
    //   294: getstatic 37	cn/testin/analysis/u:j	Ljava/util/HashMap;
    //   297: invokevirtual 84	java/util/HashMap:isEmpty	()Z
    //   300: ifeq +49 -> 349
    //   303: getstatic 495	cn/testin/analysis/u:k	Z
    //   306: ifne +43 -> 349
    //   309: iconst_1
    //   310: putstatic 495	cn/testin/analysis/u:k	Z
    //   313: getstatic 497	cn/testin/analysis/a:d	Landroid/content/Context;
    //   316: ldc -118
    //   318: invokestatic 500	cn/testin/analysis/au:a	(Landroid/content/Context;Ljava/lang/String;)Ljava/lang/String;
    //   321: invokestatic 503	cn/testin/analysis/aq:b	(Ljava/lang/String;)Ljava/util/Map;
    //   324: astore 4
    //   326: aload 4
    //   328: ifnull +21 -> 349
    //   331: aload 4
    //   333: invokeinterface 504 1 0
    //   338: ifne +11 -> 349
    //   341: getstatic 37	cn/testin/analysis/u:j	Ljava/util/HashMap;
    //   344: aload 4
    //   346: invokevirtual 505	java/util/HashMap:putAll	(Ljava/util/Map;)V
    //   349: getstatic 37	cn/testin/analysis/u:j	Ljava/util/HashMap;
    //   352: invokestatic 508	cn/testin/analysis/aq:b	(Ljava/util/Map;)Lorg/json/JSONObject;
    //   355: astore 4
    //   357: aload_3
    //   358: monitorexit
    //   359: aload 4
    //   361: ifnull +21 -> 382
    //   364: aload 4
    //   366: invokevirtual 509	org/json/JSONObject:length	()I
    //   369: ifle +13 -> 382
    //   372: aload_2
    //   373: ldc_w 511
    //   376: aload 4
    //   378: invokevirtual 403	cn/testin/analysis/ai:put	(Ljava/lang/Object;Ljava/lang/Object;)Ljava/lang/Object;
    //   381: pop
    //   382: aload_2
    //   383: invokevirtual 512	cn/testin/analysis/ai:toString	()Ljava/lang/String;
    //   386: areturn
    //   387: astore_3
    //   388: aload_3
    //   389: invokestatic 514	cn/testin/analysis/ar:a	(Ljava/lang/Throwable;)V
    //   392: goto -104 -> 288
    //   395: astore_2
    //   396: aload_3
    //   397: monitorexit
    //   398: aload_2
    //   399: athrow
    // Local variable table:
    //   start	length	slot	name	signature
    //   0	400	0	this	u
    //   0	400	1	paramBoolean	boolean
    //   7	376	2	localai	ai
    //   395	4	2	localObject1	Object
    //   387	10	3	localJSONException	JSONException
    //   324	53	4	localObject3	Object
    // Exception table:
    //   from	to	target	type
    //   75	288	387	org/json/JSONException
    //   294	326	395	finally
    //   331	349	395	finally
    //   349	359	395	finally
    //   396	398	395	finally
  }
  
  private void d()
  {
    List localList = aq.d(au.a(au.b(this.a), "pvs_triggerable"));
    if (localList != null)
    {
      this.f.clear();
      this.f.addAll(localList);
    }
  }
  
  private boolean e()
  {
    if (au.f(this.a)) {
      return false;
    }
    if (a.p) {
      return true;
    }
    return au.a("down");
  }
  
  protected Object a(String paramString)
  {
    if (TextUtils.isEmpty(paramString)) {
      return null;
    }
    label95:
    for (;;)
    {
      synchronized (this.i)
      {
        if (this.i.containsKey(paramString))
        {
          i locali = (i)this.i.get(paramString);
          if (locali != null)
          {
            paramString = locali.a;
            if (!this.f.contains(locali.b)) {
              break label95;
            }
            aa.a().a(locali.b);
            break label95;
            return paramString;
          }
        }
      }
      paramString = null;
    }
  }
  
  protected void a()
  {
    HashMap localHashMap = aq.a(au.a(au.b(this.a), "variables"));
    if (localHashMap != null)
    {
      this.i.clear();
      this.i.putAll(localHashMap);
    }
  }
  
  protected void a(OnExpUpdateListener paramOnExpUpdateListener, int paramInt, boolean paramBoolean)
  {
    if (paramOnExpUpdateListener != null) {}
    synchronized (this.d)
    {
      paramOnExpUpdateListener = new y(this, paramOnExpUpdateListener, paramInt, null);
      this.d.add(paramOnExpUpdateListener);
      this.m.post(new v(this, paramBoolean));
      return;
    }
  }
  
  protected void a(b paramb)
  {
    synchronized (this.e)
    {
      this.e.add(paramb);
      return;
    }
  }
  
  protected void a(boolean paramBoolean)
  {
    synchronized (this.h)
    {
      if (!this.g)
      {
        if (!e())
        {
          b(false);
          return;
        }
        this.g = true;
        a(ak.a, c(paramBoolean), new w(this));
      }
      return;
    }
  }
  
  protected void b()
  {
    a(null, 0, false);
  }
  
  public JSONArray c()
  {
    Object localObject2 = au.a(au.b(this.a), "currentExperimentsInfo");
    localObject1 = null;
    try
    {
      if (TextUtils.isEmpty((CharSequence)localObject2)) {
        break label163;
      }
      localObject2 = new JSONArray((String)localObject2);
      n = 0;
    }
    catch (JSONException localJSONException1)
    {
      for (;;)
      {
        int n;
        continue;
        localObject1 = null;
        continue;
        n += 1;
      }
    }
    localObject1 = localObject2;
    try
    {
      if (n >= ((JSONArray)localObject2).length()) {
        break label143;
      }
      localObject1 = ((JSONArray)localObject2).getJSONObject(n);
      String str1 = ((JSONObject)localObject1).getString("expId");
      String str2 = ((JSONObject)localObject1).getString("expVersionId");
      if ((!"CONTROL".equals(str1)) && (!"CONTROL".equals(str2)) && (aa.a().b(new Pair(str2, str1)))) {
        ((JSONObject)localObject1).put("running", true);
      } else {
        ((JSONObject)localObject1).put("running", false);
      }
    }
    catch (JSONException localJSONException2)
    {
      localObject1 = localObject2;
      localObject2 = localJSONException2;
    }
    ar.a((Throwable)localObject2);
    label143:
    localObject2 = localObject1;
    if (localObject1 == null) {
      localObject2 = new JSONArray();
    }
    return (JSONArray)localObject2;
  }
}


/* Location:              /Users/gaoht/Downloads/zirom/classes-dex2jar.jar!/cn/testin/analysis/u.class
 * Java compiler version: 6 (50.0)
 * JD-Core Version:       0.7.1
 */