package com.tendcloud.appcpa;

import android.content.BroadcastReceiver;

public class ReferralReceiver
  extends BroadcastReceiver
{
  /* Error */
  public void onReceive(android.content.Context paramContext, android.content.Intent paramIntent)
  {
    // Byte code:
    //   0: aload_2
    //   1: invokevirtual 21	android/content/Intent:getExtras	()Landroid/os/Bundle;
    //   4: astore_3
    //   5: aload_3
    //   6: ifnull +9 -> 15
    //   9: aload_3
    //   10: aconst_null
    //   11: invokevirtual 27	android/os/Bundle:containsKey	(Ljava/lang/String;)Z
    //   14: pop
    //   15: new 29	java/util/HashMap
    //   18: dup
    //   19: invokespecial 30	java/util/HashMap:<init>	()V
    //   22: pop
    //   23: aload_2
    //   24: invokevirtual 34	android/content/Intent:getAction	()Ljava/lang/String;
    //   27: ldc 36
    //   29: invokevirtual 42	java/lang/String:equals	(Ljava/lang/Object;)Z
    //   32: ifne +4 -> 36
    //   35: return
    //   36: aload_2
    //   37: ldc 44
    //   39: invokevirtual 48	android/content/Intent:getStringExtra	(Ljava/lang/String;)Ljava/lang/String;
    //   42: astore_2
    //   43: aload_2
    //   44: ifnull -9 -> 35
    //   47: aload_2
    //   48: invokevirtual 52	java/lang/String:length	()I
    //   51: ifeq -16 -> 35
    //   54: ldc 54
    //   56: aload_2
    //   57: invokestatic 60	android/util/Log:d	(Ljava/lang/String;Ljava/lang/String;)I
    //   60: pop
    //   61: aload_2
    //   62: ldc 62
    //   64: invokestatic 68	java/net/URLDecoder:decode	(Ljava/lang/String;Ljava/lang/String;)Ljava/lang/String;
    //   67: astore_2
    //   68: aload_1
    //   69: invokevirtual 74	android/content/Context:getApplicationContext	()Landroid/content/Context;
    //   72: putstatic 80	com/g/a/c:e	Landroid/content/Context;
    //   75: new 82	com/g/a/db$a
    //   78: dup
    //   79: invokespecial 83	com/g/a/db$a:<init>	()V
    //   82: astore_1
    //   83: aload_1
    //   84: getfield 87	com/g/a/db$a:a	Ljava/util/HashMap;
    //   87: ldc 89
    //   89: ldc 91
    //   91: invokevirtual 95	java/util/HashMap:put	(Ljava/lang/Object;Ljava/lang/Object;)Ljava/lang/Object;
    //   94: pop
    //   95: aload_1
    //   96: getfield 87	com/g/a/db$a:a	Ljava/util/HashMap;
    //   99: ldc 97
    //   101: iconst_1
    //   102: invokestatic 103	java/lang/Integer:valueOf	(I)Ljava/lang/Integer;
    //   105: invokevirtual 95	java/util/HashMap:put	(Ljava/lang/Object;Ljava/lang/Object;)Ljava/lang/Object;
    //   108: pop
    //   109: aload_1
    //   110: getfield 87	com/g/a/db$a:a	Ljava/util/HashMap;
    //   113: ldc 105
    //   115: ldc 107
    //   117: invokevirtual 95	java/util/HashMap:put	(Ljava/lang/Object;Ljava/lang/Object;)Ljava/lang/Object;
    //   120: pop
    //   121: aload_1
    //   122: getfield 87	com/g/a/db$a:a	Ljava/util/HashMap;
    //   125: ldc 109
    //   127: getstatic 114	com/g/a/a:a	Lcom/g/a/a;
    //   130: invokevirtual 95	java/util/HashMap:put	(Ljava/lang/Object;Ljava/lang/Object;)Ljava/lang/Object;
    //   133: pop
    //   134: new 116	java/util/TreeMap
    //   137: dup
    //   138: invokespecial 117	java/util/TreeMap:<init>	()V
    //   141: astore_3
    //   142: aload_3
    //   143: ldc 119
    //   145: aload_2
    //   146: invokeinterface 122 3 0
    //   151: pop
    //   152: aload_1
    //   153: getfield 87	com/g/a/db$a:a	Ljava/util/HashMap;
    //   156: ldc 124
    //   158: aload_3
    //   159: invokevirtual 95	java/util/HashMap:put	(Ljava/lang/Object;Ljava/lang/Object;)Ljava/lang/Object;
    //   162: pop
    //   163: invokestatic 130	com/g/a/db:c	()Landroid/os/Handler;
    //   166: bipush 102
    //   168: aload_1
    //   169: invokevirtual 136	android/os/Handler:obtainMessage	(ILjava/lang/Object;)Landroid/os/Message;
    //   172: invokevirtual 141	android/os/Message:sendToTarget	()V
    //   175: return
    //   176: astore_1
    //   177: return
    //   178: astore_1
    //   179: return
    //   180: astore_1
    //   181: return
    // Local variable table:
    //   start	length	slot	name	signature
    //   0	182	0	this	ReferralReceiver
    //   0	182	1	paramContext	android.content.Context
    //   0	182	2	paramIntent	android.content.Intent
    //   4	155	3	localObject	Object
    // Exception table:
    //   from	to	target	type
    //   68	175	176	java/lang/Throwable
    //   61	68	178	java/lang/Throwable
    //   0	5	180	java/lang/Exception
    //   9	15	180	java/lang/Exception
  }
}


/* Location:              /Users/gaoht/Downloads/zirom/classes2-dex2jar.jar!/com/tendcloud/appcpa/ReferralReceiver.class
 * Java compiler version: 6 (50.0)
 * JD-Core Version:       0.7.1
 */