package cn.jpush.android.b;

import android.os.Build.VERSION;
import cn.jiguang.net.HttpRequest;
import cn.jiguang.net.HttpResponse;
import cn.jiguang.net.HttpUtils;
import cn.jpush.android.c.f;
import com.maa.android.agent.instrumentation.Instrumented;

@Instrumented
public final class a
{
  private static final String[] z;
  
  static
  {
    String[] arrayOfString = new String[20];
    int j = 0;
    Object localObject2 = "nAw\034\001eYj\tOr\025f\024De@w\t\001cGq\003S";
    int i = -1;
    Object localObject1 = arrayOfString;
    char[] arrayOfChar = ((String)localObject2).toCharArray();
    int k = arrayOfChar.length;
    int i1 = 0;
    int m = 0;
    int i3 = i;
    localObject2 = arrayOfChar;
    int i4 = j;
    Object localObject3 = localObject1;
    int n = k;
    Object localObject4;
    int i2;
    if (k <= 1)
    {
      localObject4 = localObject1;
      localObject1 = arrayOfChar;
      i2 = i;
      label68:
      n = m;
      label71:
      localObject2 = localObject1;
      i1 = localObject2[m];
      switch (n % 5)
      {
      default: 
        i = 33;
      }
    }
    for (;;)
    {
      localObject2[m] = ((char)(i ^ i1));
      n += 1;
      if (k == 0)
      {
        m = k;
        break label71;
      }
      i1 = n;
      n = k;
      localObject3 = localObject4;
      i4 = j;
      localObject2 = localObject1;
      i3 = i2;
      i2 = i3;
      localObject1 = localObject2;
      j = i4;
      localObject4 = localObject3;
      k = n;
      m = i1;
      if (n > i1) {
        break label68;
      }
      localObject1 = new String((char[])localObject2).intern();
      switch (i3)
      {
      default: 
        localObject3[i4] = localObject1;
        j = 1;
        localObject2 = "gVw\005Nh\017k\030Uvrf\030\001+\025";
        i = 0;
        localObject1 = arrayOfString;
        break;
      case 0: 
        localObject3[i4] = localObject1;
        j = 2;
        localObject2 = "vTq\037D&Gf\037Qi[p\t\001cGq\003S";
        i = 1;
        localObject1 = arrayOfString;
        break;
      case 1: 
        localObject3[i4] = localObject1;
        j = 3;
        localObject2 = "GV`\tQr\030F\002BiQj\002F";
        i = 2;
        localObject1 = arrayOfString;
        break;
      case 2: 
        localObject3[i4] = localObject1;
        j = 4;
        localObject2 = "uAb\030Tuvl\bD<";
        i = 3;
        localObject1 = arrayOfString;
        break;
      case 3: 
        localObject3[i4] = localObject1;
        j = 5;
        localObject2 = "nAw\034\017mPf\034`j\\u\t";
        i = 4;
        localObject1 = arrayOfString;
        break;
      case 4: 
        localObject3[i4] = localObject1;
        j = 6;
        localObject2 = "EYl\037D";
        i = 5;
        localObject1 = arrayOfString;
        break;
      case 5: 
        localObject3[i4] = localObject1;
        j = 7;
        localObject2 = "TPr\031DuA#\034@r]#\bNcF#\002Nr\025f\024HuA9L\0256\001#A\001";
        i = 6;
        localObject1 = arrayOfString;
        break;
      case 6: 
        localObject3[i4] = localObject1;
        j = 8;
        localObject2 = "*\025v\036M<";
        i = 7;
        localObject1 = arrayOfString;
        break;
      case 7: 
        localObject3[i4] = localObject1;
        j = 9;
        localObject2 = "NAw\034icYs\tS";
        i = 8;
        localObject1 = arrayOfString;
        break;
      case 8: 
        localObject3[i4] = localObject1;
        j = 10;
        localObject2 = "oQf\002UoAz";
        i = 9;
        localObject1 = arrayOfString;
        break;
      case 9: 
        localObject3[i4] = localObject1;
        j = 11;
        localObject2 = "uPq\032Dt\025q\tRvZm\037D&Sb\005MsGfL\f&";
        i = 10;
        localObject1 = arrayOfString;
        break;
      case 10: 
        localObject3[i4] = localObject1;
        j = 12;
        localObject2 = "`To\037D";
        i = 11;
        localObject1 = arrayOfString;
        break;
      case 11: 
        localObject3[i4] = localObject1;
        j = 13;
        localObject2 = "BZt\002MiTgLCAf\037\001`Tj\000Db\033#+Nr\025a\025UcF#\000Dh\025?LIcTg\tS&Vl\002Uc[wLMc[d\030I(";
        i = 12;
        localObject1 = arrayOfString;
        break;
      case 12: 
        localObject3[i4] = localObject1;
        j = 14;
        localObject2 = "IAk\tS&Bq\003Oa\025q\tRvZm\037D&Fw\rUsF#A\001";
        i = 13;
        localObject1 = arrayOfString;
        break;
      case 13: 
        localObject3[i4] = localObject1;
        j = 15;
        localObject2 = "S[f\024QcVw\tE<\025g\003VhYl\rEcQ#\016XrPpLBi[w\tOr\025o\tOaAkLHu\0253";
        i = 14;
        localObject1 = arrayOfString;
        break;
      case 14: 
        localObject3[i4] = localObject1;
        j = 16;
        localObject2 = "ETw\017I&fP qcPq9OpPq\005GoPg)YePs\030Hi[/LIrAsLBj\\f\002U&P{\tBsAfLDtGl\036\000";
        i = 15;
        localObject1 = arrayOfString;
        break;
      case 15: 
        localObject3[i4] = localObject1;
        j = 17;
        localObject2 = "EZm\002DeAj\003O";
        i = 16;
        localObject1 = arrayOfString;
        break;
      case 16: 
        localObject3[i4] = localObject1;
        j = 18;
        localObject2 = "ETw\017I&tp\037DtAj\003OCGq\003S&AlL@pZj\b\001nAw\034\001eYl\037D&Vq\rRn\025.L";
        i = 17;
        localObject1 = arrayOfString;
        break;
      case 17: 
        localObject3[i4] = localObject1;
        j = 19;
        localObject2 = "gVw\005Nh\017k\030Uvfj\001QjPD\tU&\030#";
        i = 18;
        localObject1 = arrayOfString;
        break;
      case 18: 
        localObject3[i4] = localObject1;
        z = arrayOfString;
        return;
        i = 6;
        continue;
        i = 53;
        continue;
        i = 3;
        continue;
        i = 108;
      }
    }
  }
  
  public static HttpResponse a(String paramString, int paramInt, long paramLong)
  {
    f.c(z[9], z[19] + paramString);
    long l;
    if (paramLong >= 200L)
    {
      l = paramLong;
      if (paramLong <= 60000L) {}
    }
    else
    {
      l = 2000L;
    }
    Object localObject1 = null;
    paramInt = 0;
    for (;;)
    {
      try
      {
        localObject2 = new HttpRequest(paramString);
        ((HttpRequest)localObject2).setRequestProperty(z[17], z[6]);
        ((HttpRequest)localObject2).setRequestProperty(z[3], z[10]);
        if (Integer.parseInt(Build.VERSION.SDK) < 8) {
          System.setProperty(z[5], z[12]);
        }
        localObject2 = HttpUtils.httpGet(null, (HttpRequest)localObject2);
      }
      catch (AssertionError localAssertionError1)
      {
        Object localObject2;
        int i;
        continue;
      }
      catch (Exception localException1)
      {
        continue;
      }
      try
      {
        i = ((HttpResponse)localObject2).getResponseCode();
        f.a(z[9], z[4] + i);
        localObject1 = localObject2;
        if (i == 200) {
          return (HttpResponse)localObject2;
        }
      }
      catch (Exception localException2)
      {
        localObject1 = localObject2;
        localObject2 = localException2;
        f.a(z[9], z[0], (Throwable)localObject2);
        localObject2 = localObject1;
        if (paramInt < 5) {
          paramInt += 1;
        }
      }
      catch (AssertionError localAssertionError2)
      {
        try
        {
          Thread.sleep(l);
        }
        catch (InterruptedException localInterruptedException) {}
        localAssertionError2 = localAssertionError2;
        localObject1 = localObject2;
        localObject2 = localAssertionError2;
        f.i(z[9], z[18] + ((AssertionError)localObject2).toString());
      }
    }
  }
  
  public static byte[] a(String paramString, int paramInt1, long paramLong, int paramInt2)
  {
    byte[] arrayOfByte1 = null;
    paramInt1 = 0;
    byte[] arrayOfByte2;
    for (;;)
    {
      arrayOfByte2 = arrayOfByte1;
      if (paramInt1 >= 4) {
        break;
      }
      arrayOfByte1 = b(paramString, 5, 5000L);
      arrayOfByte2 = arrayOfByte1;
      if (arrayOfByte1 != null) {
        break;
      }
      paramInt1 += 1;
    }
    return arrayOfByte2;
  }
  
  /* Error */
  private static byte[] b(String paramString, int paramInt, long paramLong)
  {
    // Byte code:
    //   0: iload_1
    //   1: ifle +12 -> 13
    //   4: iload_1
    //   5: istore 4
    //   7: iload_1
    //   8: bipush 10
    //   10: if_icmple +6 -> 16
    //   13: iconst_1
    //   14: istore 4
    //   16: lload_2
    //   17: ldc2_w 93
    //   20: lcmp
    //   21: iflt +14 -> 35
    //   24: lload_2
    //   25: lstore 7
    //   27: lload_2
    //   28: ldc2_w 95
    //   31: lcmp
    //   32: ifle +8 -> 40
    //   35: ldc2_w 97
    //   38: lstore 7
    //   40: getstatic 65	cn/jpush/android/b/a:z	[Ljava/lang/String;
    //   43: bipush 9
    //   45: aaload
    //   46: new 76	java/lang/StringBuilder
    //   49: dup
    //   50: getstatic 65	cn/jpush/android/b/a:z	[Ljava/lang/String;
    //   53: iconst_1
    //   54: aaload
    //   55: invokespecial 79	java/lang/StringBuilder:<init>	(Ljava/lang/String;)V
    //   58: aload_0
    //   59: invokevirtual 83	java/lang/StringBuilder:append	(Ljava/lang/String;)Ljava/lang/StringBuilder;
    //   62: invokevirtual 86	java/lang/StringBuilder:toString	()Ljava/lang/String;
    //   65: invokestatic 92	cn/jpush/android/c/f:c	(Ljava/lang/String;Ljava/lang/String;)V
    //   68: iconst_0
    //   69: istore_1
    //   70: aconst_null
    //   71: astore 10
    //   73: aconst_null
    //   74: astore 11
    //   76: aload 10
    //   78: astore 13
    //   80: aload 11
    //   82: astore 12
    //   84: new 165	java/net/URL
    //   87: dup
    //   88: aload_0
    //   89: invokespecial 166	java/net/URL:<init>	(Ljava/lang/String;)V
    //   92: astore 9
    //   94: aload 10
    //   96: astore 13
    //   98: aload 11
    //   100: astore 12
    //   102: aload 9
    //   104: instanceof 165
    //   107: ifne +212 -> 319
    //   110: aload 10
    //   112: astore 13
    //   114: aload 11
    //   116: astore 12
    //   118: aload 9
    //   120: invokevirtual 170	java/net/URL:openConnection	()Ljava/net/URLConnection;
    //   123: astore 9
    //   125: aload 10
    //   127: astore 13
    //   129: aload 11
    //   131: astore 12
    //   133: aload 9
    //   135: checkcast 172	java/net/HttpURLConnection
    //   138: astore 9
    //   140: aload 9
    //   142: getstatic 65	cn/jpush/android/b/a:z	[Ljava/lang/String;
    //   145: iconst_3
    //   146: aaload
    //   147: getstatic 65	cn/jpush/android/b/a:z	[Ljava/lang/String;
    //   150: bipush 10
    //   152: aaload
    //   153: invokevirtual 173	java/net/HttpURLConnection:setRequestProperty	(Ljava/lang/String;Ljava/lang/String;)V
    //   156: aload 9
    //   158: getstatic 65	cn/jpush/android/b/a:z	[Ljava/lang/String;
    //   161: bipush 17
    //   163: aaload
    //   164: getstatic 65	cn/jpush/android/b/a:z	[Ljava/lang/String;
    //   167: bipush 6
    //   169: aaload
    //   170: invokevirtual 176	java/net/HttpURLConnection:addRequestProperty	(Ljava/lang/String;Ljava/lang/String;)V
    //   173: getstatic 110	android/os/Build$VERSION:SDK	Ljava/lang/String;
    //   176: invokestatic 116	java/lang/Integer:parseInt	(Ljava/lang/String;)I
    //   179: bipush 8
    //   181: if_icmpge +18 -> 199
    //   184: getstatic 65	cn/jpush/android/b/a:z	[Ljava/lang/String;
    //   187: iconst_5
    //   188: aaload
    //   189: getstatic 65	cn/jpush/android/b/a:z	[Ljava/lang/String;
    //   192: bipush 12
    //   194: aaload
    //   195: invokestatic 122	java/lang/System:setProperty	(Ljava/lang/String;Ljava/lang/String;)Ljava/lang/String;
    //   198: pop
    //   199: aload 9
    //   201: invokevirtual 177	java/net/HttpURLConnection:getResponseCode	()I
    //   204: istore 5
    //   206: getstatic 65	cn/jpush/android/b/a:z	[Ljava/lang/String;
    //   209: bipush 9
    //   211: aaload
    //   212: new 76	java/lang/StringBuilder
    //   215: dup
    //   216: getstatic 65	cn/jpush/android/b/a:z	[Ljava/lang/String;
    //   219: iconst_4
    //   220: aaload
    //   221: invokespecial 79	java/lang/StringBuilder:<init>	(Ljava/lang/String;)V
    //   224: iload 5
    //   226: invokevirtual 137	java/lang/StringBuilder:append	(I)Ljava/lang/StringBuilder;
    //   229: invokevirtual 86	java/lang/StringBuilder:toString	()Ljava/lang/String;
    //   232: invokestatic 139	cn/jpush/android/c/f:a	(Ljava/lang/String;Ljava/lang/String;)V
    //   235: iload 5
    //   237: sipush 200
    //   240: if_icmpne +100 -> 340
    //   243: aload 9
    //   245: invokevirtual 180	java/net/HttpURLConnection:getContentLength	()I
    //   248: istore 6
    //   250: aload 9
    //   252: invokevirtual 184	java/net/HttpURLConnection:getInputStream	()Ljava/io/InputStream;
    //   255: astore 11
    //   257: aload 11
    //   259: ifnull +592 -> 851
    //   262: aload 11
    //   264: invokestatic 188	cn/jiguang/net/HttpUtils:readInputStream	(Ljava/io/InputStream;)[B
    //   267: astore 10
    //   269: aload 11
    //   271: ifnull +8 -> 279
    //   274: aload 11
    //   276: invokevirtual 193	java/io/InputStream:close	()V
    //   279: aload 9
    //   281: ifnull +8 -> 289
    //   284: aload 9
    //   286: invokevirtual 196	java/net/HttpURLConnection:disconnect	()V
    //   289: sipush 200
    //   292: iload 5
    //   294: if_icmpne +322 -> 616
    //   297: iload 6
    //   299: ifne +271 -> 570
    //   302: getstatic 65	cn/jpush/android/b/a:z	[Ljava/lang/String;
    //   305: bipush 9
    //   307: aaload
    //   308: getstatic 65	cn/jpush/android/b/a:z	[Ljava/lang/String;
    //   311: bipush 15
    //   313: aaload
    //   314: invokestatic 92	cn/jpush/android/c/f:c	(Ljava/lang/String;Ljava/lang/String;)V
    //   317: aconst_null
    //   318: areturn
    //   319: aload 10
    //   321: astore 13
    //   323: aload 11
    //   325: astore 12
    //   327: aload 9
    //   329: checkcast 165	java/net/URL
    //   332: invokestatic 201	com/mato/sdk/instrumentation/HttpInstrumentation:openConnection	(Ljava/net/URL;)Ljava/net/URLConnection;
    //   335: astore 9
    //   337: goto -212 -> 125
    //   340: aload 10
    //   342: ifnull +8 -> 350
    //   345: aload 10
    //   347: invokevirtual 193	java/io/InputStream:close	()V
    //   350: aload 9
    //   352: ifnull +492 -> 844
    //   355: aload 9
    //   357: invokevirtual 196	java/net/HttpURLConnection:disconnect	()V
    //   360: aload 10
    //   362: astore 12
    //   364: iload_1
    //   365: iload 4
    //   367: if_icmplt +165 -> 532
    //   370: aconst_null
    //   371: areturn
    //   372: astore 10
    //   374: aload 9
    //   376: astore 10
    //   378: aload 11
    //   380: astore 9
    //   382: getstatic 65	cn/jpush/android/b/a:z	[Ljava/lang/String;
    //   385: bipush 9
    //   387: aaload
    //   388: getstatic 65	cn/jpush/android/b/a:z	[Ljava/lang/String;
    //   391: bipush 16
    //   393: aaload
    //   394: invokestatic 204	cn/jpush/android/c/f:j	(Ljava/lang/String;Ljava/lang/String;)V
    //   397: aload 9
    //   399: ifnull +8 -> 407
    //   402: aload 9
    //   404: invokevirtual 193	java/io/InputStream:close	()V
    //   407: aload 10
    //   409: ifnull +448 -> 857
    //   412: aload 10
    //   414: invokevirtual 196	java/net/HttpURLConnection:disconnect	()V
    //   417: aload 9
    //   419: astore 12
    //   421: aload 10
    //   423: astore 9
    //   425: goto -61 -> 364
    //   428: astore 12
    //   430: aload 11
    //   432: astore 10
    //   434: aload 9
    //   436: astore 11
    //   438: aload 12
    //   440: astore 9
    //   442: aload 10
    //   444: astore 13
    //   446: aload 11
    //   448: astore 12
    //   450: getstatic 65	cn/jpush/android/b/a:z	[Ljava/lang/String;
    //   453: bipush 9
    //   455: aaload
    //   456: getstatic 65	cn/jpush/android/b/a:z	[Ljava/lang/String;
    //   459: iconst_0
    //   460: aaload
    //   461: aload 9
    //   463: invokestatic 142	cn/jpush/android/c/f:a	(Ljava/lang/String;Ljava/lang/String;Ljava/lang/Throwable;)V
    //   466: aload 10
    //   468: ifnull +8 -> 476
    //   471: aload 10
    //   473: invokevirtual 193	java/io/InputStream:close	()V
    //   476: aload 10
    //   478: astore 12
    //   480: aload 11
    //   482: astore 9
    //   484: aload 11
    //   486: ifnull -122 -> 364
    //   489: aload 11
    //   491: invokevirtual 196	java/net/HttpURLConnection:disconnect	()V
    //   494: aload 10
    //   496: astore 12
    //   498: aload 11
    //   500: astore 9
    //   502: goto -138 -> 364
    //   505: astore_0
    //   506: aload 11
    //   508: astore 10
    //   510: aload 10
    //   512: ifnull +8 -> 520
    //   515: aload 10
    //   517: invokevirtual 193	java/io/InputStream:close	()V
    //   520: aload 9
    //   522: ifnull +8 -> 530
    //   525: aload 9
    //   527: invokevirtual 196	java/net/HttpURLConnection:disconnect	()V
    //   530: aload_0
    //   531: athrow
    //   532: iload_1
    //   533: iconst_1
    //   534: iadd
    //   535: istore_1
    //   536: iload_1
    //   537: i2l
    //   538: lstore_2
    //   539: lload_2
    //   540: lload 7
    //   542: lmul
    //   543: invokestatic 148	java/lang/Thread:sleep	(J)V
    //   546: aload 12
    //   548: astore 10
    //   550: aload 9
    //   552: astore 11
    //   554: goto -478 -> 76
    //   557: astore 10
    //   559: aload 12
    //   561: astore 10
    //   563: aload 9
    //   565: astore 11
    //   567: goto -491 -> 76
    //   570: aload 10
    //   572: arraylength
    //   573: iload 6
    //   575: if_icmpge +20 -> 595
    //   578: getstatic 65	cn/jpush/android/b/a:z	[Ljava/lang/String;
    //   581: bipush 9
    //   583: aaload
    //   584: getstatic 65	cn/jpush/android/b/a:z	[Ljava/lang/String;
    //   587: bipush 13
    //   589: aaload
    //   590: invokestatic 92	cn/jpush/android/c/f:c	(Ljava/lang/String;Ljava/lang/String;)V
    //   593: aconst_null
    //   594: areturn
    //   595: aload 10
    //   597: areturn
    //   598: astore_0
    //   599: getstatic 65	cn/jpush/android/b/a:z	[Ljava/lang/String;
    //   602: bipush 9
    //   604: aaload
    //   605: getstatic 65	cn/jpush/android/b/a:z	[Ljava/lang/String;
    //   608: iconst_2
    //   609: aaload
    //   610: aload_0
    //   611: invokestatic 142	cn/jpush/android/c/f:a	(Ljava/lang/String;Ljava/lang/String;Ljava/lang/Throwable;)V
    //   614: aconst_null
    //   615: areturn
    //   616: sipush 400
    //   619: iload 5
    //   621: if_icmpne +34 -> 655
    //   624: getstatic 65	cn/jpush/android/b/a:z	[Ljava/lang/String;
    //   627: bipush 9
    //   629: aaload
    //   630: new 76	java/lang/StringBuilder
    //   633: dup
    //   634: getstatic 65	cn/jpush/android/b/a:z	[Ljava/lang/String;
    //   637: bipush 11
    //   639: aaload
    //   640: invokespecial 79	java/lang/StringBuilder:<init>	(Ljava/lang/String;)V
    //   643: aload_0
    //   644: invokevirtual 83	java/lang/StringBuilder:append	(Ljava/lang/String;)Ljava/lang/StringBuilder;
    //   647: invokevirtual 86	java/lang/StringBuilder:toString	()Ljava/lang/String;
    //   650: invokestatic 92	cn/jpush/android/c/f:c	(Ljava/lang/String;Ljava/lang/String;)V
    //   653: aconst_null
    //   654: areturn
    //   655: sipush 404
    //   658: iload 5
    //   660: if_icmpne +34 -> 694
    //   663: getstatic 65	cn/jpush/android/b/a:z	[Ljava/lang/String;
    //   666: bipush 9
    //   668: aaload
    //   669: new 76	java/lang/StringBuilder
    //   672: dup
    //   673: getstatic 65	cn/jpush/android/b/a:z	[Ljava/lang/String;
    //   676: bipush 7
    //   678: aaload
    //   679: invokespecial 79	java/lang/StringBuilder:<init>	(Ljava/lang/String;)V
    //   682: aload_0
    //   683: invokevirtual 83	java/lang/StringBuilder:append	(Ljava/lang/String;)Ljava/lang/StringBuilder;
    //   686: invokevirtual 86	java/lang/StringBuilder:toString	()Ljava/lang/String;
    //   689: invokestatic 92	cn/jpush/android/c/f:c	(Ljava/lang/String;Ljava/lang/String;)V
    //   692: aconst_null
    //   693: areturn
    //   694: getstatic 65	cn/jpush/android/b/a:z	[Ljava/lang/String;
    //   697: bipush 9
    //   699: aaload
    //   700: new 76	java/lang/StringBuilder
    //   703: dup
    //   704: getstatic 65	cn/jpush/android/b/a:z	[Ljava/lang/String;
    //   707: bipush 14
    //   709: aaload
    //   710: invokespecial 79	java/lang/StringBuilder:<init>	(Ljava/lang/String;)V
    //   713: iload 5
    //   715: invokevirtual 137	java/lang/StringBuilder:append	(I)Ljava/lang/StringBuilder;
    //   718: getstatic 65	cn/jpush/android/b/a:z	[Ljava/lang/String;
    //   721: bipush 8
    //   723: aaload
    //   724: invokevirtual 83	java/lang/StringBuilder:append	(Ljava/lang/String;)Ljava/lang/StringBuilder;
    //   727: aload_0
    //   728: invokevirtual 83	java/lang/StringBuilder:append	(Ljava/lang/String;)Ljava/lang/StringBuilder;
    //   731: invokevirtual 86	java/lang/StringBuilder:toString	()Ljava/lang/String;
    //   734: invokestatic 92	cn/jpush/android/c/f:c	(Ljava/lang/String;Ljava/lang/String;)V
    //   737: aconst_null
    //   738: areturn
    //   739: astore 11
    //   741: goto -462 -> 279
    //   744: astore 11
    //   746: goto -396 -> 350
    //   749: astore 11
    //   751: goto -344 -> 407
    //   754: astore 9
    //   756: goto -280 -> 476
    //   759: astore 10
    //   761: goto -241 -> 520
    //   764: astore_0
    //   765: aload 10
    //   767: astore 11
    //   769: aload 9
    //   771: astore 10
    //   773: aload 11
    //   775: astore 9
    //   777: goto -267 -> 510
    //   780: astore_0
    //   781: aload 13
    //   783: astore 10
    //   785: aload 12
    //   787: astore 9
    //   789: goto -279 -> 510
    //   792: astore_0
    //   793: goto -283 -> 510
    //   796: astore 9
    //   798: goto -356 -> 442
    //   801: astore 12
    //   803: aload 9
    //   805: astore 11
    //   807: aload 12
    //   809: astore 9
    //   811: goto -369 -> 442
    //   814: astore 9
    //   816: aload 10
    //   818: astore 9
    //   820: aload 11
    //   822: astore 10
    //   824: goto -442 -> 382
    //   827: astore 11
    //   829: aload 9
    //   831: astore 11
    //   833: aload 10
    //   835: astore 9
    //   837: aload 11
    //   839: astore 10
    //   841: goto -459 -> 382
    //   844: aload 10
    //   846: astore 12
    //   848: goto -484 -> 364
    //   851: aconst_null
    //   852: astore 10
    //   854: goto -585 -> 269
    //   857: aload 9
    //   859: astore 12
    //   861: aload 10
    //   863: astore 9
    //   865: goto -501 -> 364
    // Local variable table:
    //   start	length	slot	name	signature
    //   0	868	0	paramString	String
    //   0	868	1	paramInt	int
    //   0	868	2	paramLong	long
    //   5	363	4	i	int
    //   204	510	5	j	int
    //   248	328	6	k	int
    //   25	516	7	l	long
    //   92	472	9	localObject1	Object
    //   754	16	9	localIOException1	java.io.IOException
    //   775	13	9	localObject2	Object
    //   796	8	9	localException1	Exception
    //   809	1	9	localException2	Exception
    //   814	1	9	localSSLPeerUnverifiedException1	javax.net.ssl.SSLPeerUnverifiedException
    //   818	46	9	localObject3	Object
    //   71	290	10	arrayOfByte	byte[]
    //   372	1	10	localSSLPeerUnverifiedException2	javax.net.ssl.SSLPeerUnverifiedException
    //   376	173	10	localObject4	Object
    //   557	1	10	localInterruptedException	InterruptedException
    //   561	35	10	localObject5	Object
    //   759	7	10	localIOException2	java.io.IOException
    //   771	91	10	localObject6	Object
    //   74	492	11	localObject7	Object
    //   739	1	11	localIOException3	java.io.IOException
    //   744	1	11	localIOException4	java.io.IOException
    //   749	1	11	localIOException5	java.io.IOException
    //   767	54	11	localObject8	Object
    //   827	1	11	localSSLPeerUnverifiedException3	javax.net.ssl.SSLPeerUnverifiedException
    //   831	7	11	localObject9	Object
    //   82	338	12	localObject10	Object
    //   428	11	12	localException3	Exception
    //   448	338	12	localObject11	Object
    //   801	7	12	localException4	Exception
    //   846	14	12	localObject12	Object
    //   78	704	13	localObject13	Object
    // Exception table:
    //   from	to	target	type
    //   262	269	372	javax/net/ssl/SSLPeerUnverifiedException
    //   262	269	428	java/lang/Exception
    //   262	269	505	finally
    //   539	546	557	java/lang/InterruptedException
    //   302	317	598	java/lang/Exception
    //   570	593	598	java/lang/Exception
    //   274	279	739	java/io/IOException
    //   345	350	744	java/io/IOException
    //   402	407	749	java/io/IOException
    //   471	476	754	java/io/IOException
    //   515	520	759	java/io/IOException
    //   382	397	764	finally
    //   84	94	780	finally
    //   102	110	780	finally
    //   118	125	780	finally
    //   133	140	780	finally
    //   327	337	780	finally
    //   450	466	780	finally
    //   140	199	792	finally
    //   199	235	792	finally
    //   243	257	792	finally
    //   84	94	796	java/lang/Exception
    //   102	110	796	java/lang/Exception
    //   118	125	796	java/lang/Exception
    //   133	140	796	java/lang/Exception
    //   327	337	796	java/lang/Exception
    //   140	199	801	java/lang/Exception
    //   199	235	801	java/lang/Exception
    //   243	257	801	java/lang/Exception
    //   84	94	814	javax/net/ssl/SSLPeerUnverifiedException
    //   102	110	814	javax/net/ssl/SSLPeerUnverifiedException
    //   118	125	814	javax/net/ssl/SSLPeerUnverifiedException
    //   133	140	814	javax/net/ssl/SSLPeerUnverifiedException
    //   327	337	814	javax/net/ssl/SSLPeerUnverifiedException
    //   140	199	827	javax/net/ssl/SSLPeerUnverifiedException
    //   199	235	827	javax/net/ssl/SSLPeerUnverifiedException
    //   243	257	827	javax/net/ssl/SSLPeerUnverifiedException
  }
}


/* Location:              /Users/gaoht/Downloads/zirom/classes-dex2jar.jar!/cn/jpush/android/b/a.class
 * Java compiler version: 6 (50.0)
 * JD-Core Version:       0.7.1
 */